Workbook
Name Bank_credit_to_GDP_ratio__2_year_av._change: OFFSET(INDIRECT("'1.1. SRI PT'!$p$"&'[1]1.1. SRI PT'!$A$1),0,0,COUNTIFS('[1]1.1. SRI PT'!$D:$D,"<>",'[1]1.1. SRI PT'!$D:$D,"<>#N/A")- 1)
Name CI_normalized_pooled_data: OFFSET(INDIRECT("'1.1. SRI PT'!$D$"&'[1]1.1. SRI PT'!$A$1),0,0,COUNTIFS('[1]1.1. SRI PT'!$D:$D,"<>",'[1]1.1. SRI PT'!$D:$D,"<>#N/A") - 1)
Name CI_normalized_with_country_data: OFFSET(INDIRECT("'1.1. SRI PT'!$E$"&'[1]1.1. SRI PT'!$A$1),0,0,COUNTIFS('[1]1.1. SRI PT'!$E:$E,"<>",'[1]1.1. SRI PT'!$E:$E,"<>#N/A") - 1)
Name CI_normalized_with_country_data_real_time: OFFSET(INDIRECT("'1.1. SRI PT'!$G$"&'[1]1.1. SRI PT'!$A$1),0,0,COUNTIFS('[1]1.1. SRI PT'!$G:$G,"<>",'[1]1.1. SRI PT'!$G:$G,"<>#N/A") - 1)
Name CI_normalized_with_pooled_data__average_weights: OFFSET(INDIRECT("'1.1. SRI PT'!$U$"&'[1]1.1. SRI PT'!$A$1),0,0,COUNTIFS('[1]1.1. SRI PT'!#REF!,"<>",'[1]1.1. SRI PT'!#REF!,"<>#N/A") - 1)
Name CI_normalized_with_pooled_data__average_weights: OFFSET(INDIRECT("'1.1. SRI PT'!$U$"&'[1]1.1. SRI PT'!$A$1),0,0,COUNTIFS('[1]1.1. SRI PT'!#REF!,"<>",'[1]1.1. SRI PT'!#REF!,"<>#N/A") - 1)
Name CI_normalized_with_pooled_data_real_time: OFFSET(INDIRECT("'1.1. SRI PT'!$F$"&'[1]1.1. SRI PT'!$A$1),0,0,COUNTIFS('[1]1.1. SRI PT'!$F:$F,"<>",'[1]1.1. SRI PT'!$F:$F,"<>#N/A") - 1)
Name Crisis_onset: OFFSET(INDIRECT("'aux'!$B$"&[1]aux!$I$1),0,0,COUNTIFS('[1]1.1. SRI PT'!$D:$D,"<>",'[1]1.1. SRI PT'!$D:$D,"<>#N/A")- 1)
Name Current_account_to_GDP: OFFSET(INDIRECT("'1.1. SRI PT'!$s$"&'[1]1.1. SRI PT'!$A$1),0,0,COUNTIFS('[1]1.1. SRI PT'!$D:$D,"<>",'[1]1.1. SRI PT'!$D:$D,"<>#N/A")- 1)
Name date: OFFSET(INDIRECT("'1.1. SRI PT'!$C$"&'[1]1.1. SRI PT'!$A$1),0,0,COUNTIFS('[1]1.1. SRI PT'!$D:$D,"<>",'[1]1.1. SRI PT'!$D:$D,"<>#N/A")- 1)
Name date2: OFFSET(INDIRECT("'aux'!$A$"&[1]aux!$I$1),0,0,COUNTIFS('[1]1.1. SRI PT'!$D:$D,"<>",'[1]1.1. SRI PT'!$D:$D,"<>#N/A")- 1)
Name dateT: OFFSET(INDIRECT("'1.1. SRI PT'!$T$"&'[1]1.1. SRI PT'!$A$1),0,0,COUNTIFS('[1]1.1. SRI PT'!$D:$D,"<>",'[1]1.1. SRI PT'!$D:$D,"<>#N/A")- 1)
Name Debt_service_ratio__2_year_av._change: OFFSET(INDIRECT("'1.1. SRI PT'!$r$"&'[1]1.1. SRI PT'!$A$1),0,0,COUNTIFS('[1]1.1. SRI PT'!$D:$D,"<>",'[1]1.1. SRI PT'!$D:$D,"<>#N/A")- 1)
Name Evaluation_period: OFFSET(INDIRECT("'aux'!$C$"&[1]aux!$I$1),0,0,COUNTIFS('[1]1.1. SRI PT'!$D:$D,"<>",'[1]1.1. SRI PT'!$D:$D,"<>#N/A")- 1)
Name Low_threshold: OFFSET(INDIRECT("'aux'!$D$"&[1]aux!$I$1),0,0,COUNTIFS('[1]1.1. SRI PT'!$D:$D,"<>",'[1]1.1. SRI PT'!$D:$D,"<>#N/A")- 1)
Name Medium_threshold: OFFSET(INDIRECT("'aux'!$E$"&[1]aux!$I$1),0,0,COUNTIFS('[1]1.1. SRI PT'!$D:$D,"<>",'[1]1.1. SRI PT'!$D:$D,"<>#N/A")- 1)
Name Real_total_credit__2_year_av._growth: OFFSET(INDIRECT("'1.1. SRI PT'!$o$"&'[1]1.1. SRI PT'!$A$1),0,0,COUNTIFS('[1]1.1. SRI PT'!$D:$D,"<>",'[1]1.1. SRI PT'!$D:$D,"<>#N/A")- 1)
Name RRE_price_to_income_ratio__3_year_av._change: OFFSET(INDIRECT("'1.1. SRI PT'!$q$"&'[1]1.1. SRI PT'!$A$1),0,0,COUNTIFS('[1]1.1. SRI PT'!$D:$D,"<>",'[1]1.1. SRI PT'!$D:$D,"<>#N/A")- 1)

Sheet Scoreboard
C1: 2022Q1 | D1: C1 | E1: C2 | F1: C3 | G1: C4 | H1: C5 | I1: C6 | J1: C7 | K1: C8 | L1: C9 | M1: C10 | N1: C11
C2: ="Date:" &C1 -> Date:2022Q1
D3: ="Cálculos do Banco de Portugal - Tabela com dados para " & C1 -> Cálculos do Banco de Portugal - Tabela com dados para 2022Q1
D4: Indicators
C5: Country | D5: Bank credit-to-GDP ratio, 2-year av. change | E5: Real total credit, 2-year av. Growth | F5: Current account balance, % of GDP | G5: NFPS lending spreads, 2-year av. Change | H5: Bank credit-to-GDP gap | I5: Total credit-to-GDP gap | J5: Loans to HHs for house purchases, 3-year av. Growth | K5: HH debt, % of income | L5: RRE price-to-income ratio, 3-year av. growth | M5: Real house price growth, 3-year av. Growth | N5: Debt service ratio, 2-year av. Change
B6: AT | C6: Austria | D6: =VLOOKUP($B6&$C$1,data_stata!$A:$P,MATCH(Scoreboard!D$1,data_stata!$A$1:$P$1,0),FALSE) -> 2.4189949 | E6: =VLOOKUP($B6&$C$1,data_stata!$A:$P,MATCH(Scoreboard!E$1,data_stata!$A$1:$P$1,0),FALSE) -> 0.82022309 | F6: =VLOOKUP($B6&$C$1,data_stata!$A:$P,MATCH(Scoreboard!F$1,data_stata!$A$1:$P$1,0),FALSE) -> -0.0079380581 | G6: =VLOOKUP($B6&$C$1,data_stata!$A:$P,MATCH(Scoreboard!G$1,data_stata!$A$1:$P$1,0),FALSE) -> 0.041655581 | H6: =VLOOKUP($B6&$C$1,data_stata!$A:$P,MATCH(Scoreboard!H$1,data_stata!$A$1:$P$1,0),FALSE) -> 3.7858102 | I6: =VLOOKUP($B6&$C$1,data_stata!$A:$P,MATCH(Scoreboard!I$1,data_stata!$A$1:$P$1,0),FALSE) -> 0.0011330439 | J6: =VLOOKUP($B6&$C$1,data_stata!$A:$P,MATCH(Scoreboard!J$1,data_stata!$A$1:$P$1,0),FALSE) -> 3.7871227 | K6: =VLOOKUP($B6&$C$1,data_stata!$A:$P,MATCH(Scoreboard!K$1,data_stata!$A$1:$P$1,0),FALSE) -> 86.340889 | ... N6: =VLOOKUP($B6&$C$1,data_stata!$A:$P,MATCH(Scoreboard!N$1,data_stata!$A$1:$P$1,0),FALSE) -> 0.10050106
B7: BE | C7: Belgium | D7: =VLOOKUP($B7&$C$1,data_stata!$A:$P,MATCH(Scoreboard!D$1,data_stata!$A$1:$P$1,0),FALSE) -> -0.01348877 | E7: =VLOOKUP($B7&$C$1,data_stata!$A:$P,MATCH(Scoreboard!E$1,data_stata!$A$1:$P$1,0),FALSE) -> 0.12804413 | F7: =VLOOKUP($B7&$C$1,data_stata!$A:$P,MATCH(Scoreboard!F$1,data_stata!$A$1:$P$1,0),FALSE) -> -0.69614112 | G7: =VLOOKUP($B7&$C$1,data_stata!$A:$P,MATCH(Scoreboard!G$1,data_stata!$A$1:$P$1,0),FALSE) -> 0.080625445 | H7: =VLOOKUP($B7&$C$1,data_stata!$A:$P,MATCH(Scoreboard!H$1,data_stata!$A$1:$P$1,0),FALSE) -> -3.3723118 | I7: =VLOOKUP($B7&$C$1,data_stata!$A:$P,MATCH(Scoreboard!I$1,data_stata!$A$1:$P$1,0),FALSE) -> -18.684326 | J7: =VLOOKUP($B7&$C$1,data_stata!$A:$P,MATCH(Scoreboard!J$1,data_stata!$A$1:$P$1,0),FALSE) -> 6.2709517 | K7: =VLOOKUP($B7&$C$1,data_stata!$A:$P,MATCH(Scoreboard!K$1,data_stata!$A$1:$P$1,0),FALSE) -> 106.14912 | ... N7: =VLOOKUP($B7&$C$1,data_stata!$A:$P,MATCH(Scoreboard!N$1,data_stata!$A$1:$P$1,0),FALSE) -> -0.43176937
B8: CY | C8: Cyprus | D8: =VLOOKUP($B8&$C$1,data_stata!$A:$P,MATCH(Scoreboard!D$1,data_stata!$A$1:$P$1,0),FALSE) -> -17.867874 | E8: =VLOOKUP($B8&$C$1,data_stata!$A:$P,MATCH(Scoreboard!E$1,data_stata!$A$1:$P$1,0),FALSE) -> -2.6303473 | F8: =VLOOKUP($B8&$C$1,data_stata!$A:$P,MATCH(Scoreboard!F$1,data_stata!$A$1:$P$1,0),FALSE) -> -7.8746452 | G8: =VLOOKUP($B8&$C$1,data_stata!$A:$P,MATCH(Scoreboard!G$1,data_stata!$A$1:$P$1,0),FALSE) -> -0.0010982448 | H8: =VLOOKUP($B8&$C$1,data_stata!$A:$P,MATCH(Scoreboard!H$1,data_stata!$A$1:$P$1,0),FALSE) -> -64.152016 | I8: =VLOOKUP($B8&$C$1,data_stata!$A:$P,MATCH(Scoreboard!I$1,data_stata!$A$1:$P$1,0),FALSE) -> -71.318222 | J8: =VLOOKUP($B8&$C$1,data_stata!$A:$P,MATCH(Scoreboard!J$1,data_stata!$A$1:$P$1,0),FALSE) -> -2.8121607 | K8: =VLOOKUP($B8&$C$1,data_stata!$A:$P,MATCH(Scoreboard!K$1,data_stata!$A$1:$P$1,0),FALSE) -> 0 | ... N8: =VLOOKUP($B8&$C$1,data_stata!$A:$P,MATCH(Scoreboard!N$1,data_stata!$A$1:$P$1,0),FALSE) -> -1.6748018
B9: DE | C9: Germany | D9: =VLOOKUP($B9&$C$1,data_stata!$A:$P,MATCH(Scoreboard!D$1,data_stata!$A$1:$P$1,0),FALSE) -> 1.6624985 | E9: =VLOOKUP($B9&$C$1,data_stata!$A:$P,MATCH(Scoreboard!E$1,data_stata!$A$1:$P$1,0),FALSE) -> 2.0945835 | F9: =VLOOKUP($B9&$C$1,data_stata!$A:$P,MATCH(Scoreboard!F$1,data_stata!$A$1:$P$1,0),FALSE) -> 6.5920005 | G9: =VLOOKUP($B9&$C$1,data_stata!$A:$P,MATCH(Scoreboard!G$1,data_stata!$A$1:$P$1,0),FALSE) -> 0.27494881 | H9: =VLOOKUP($B9&$C$1,data_stata!$A:$P,MATCH(Scoreboard!H$1,data_stata!$A$1:$P$1,0),FALSE) -> 7.1283059 | I9: =VLOOKUP($B9&$C$1,data_stata!$A:$P,MATCH(Scoreboard!I$1,data_stata!$A$1:$P$1,0),FALSE) -> 10.17368 | J9: =VLOOKUP($B9&$C$1,data_stata!$A:$P,MATCH(Scoreboard!J$1,data_stata!$A$1:$P$1,0),FALSE) -> 3.594506 | K9: =VLOOKUP($B9&$C$1,data_stata!$A:$P,MATCH(Scoreboard!K$1,data_stata!$A$1:$P$1,0),FALSE) -> 91.701042 | ... N9: =VLOOKUP($B9&$C$1,data_stata!$A:$P,MATCH(Scoreboard!N$1,data_stata!$A$1:$P$1,0),FALSE) -> 0.027908325
B10: EE | C10: Estonia | D10: =VLOOKUP($B10&$C$1,data_stata!$A:$P,MATCH(Scoreboard!D$1,data_stata!$A$1:$P$1,0),FALSE) -> -1.4638519 | E10: =VLOOKUP($B10&$C$1,data_stata!$A:$P,MATCH(Scoreboard!E$1,data_stata!$A$1:$P$1,0),FALSE) -> 0.72803152 | F10: =VLOOKUP($B10&$C$1,data_stata!$A:$P,MATCH(Scoreboard!F$1,data_stata!$A$1:$P$1,0),FALSE) -> -0.17791331 | G10: =VLOOKUP($B10&$C$1,data_stata!$A:$P,MATCH(Scoreboard!G$1,data_stata!$A$1:$P$1,0),FALSE) -> 0.14534177 | H10: =VLOOKUP($B10&$C$1,data_stata!$A:$P,MATCH(Scoreboard!H$1,data_stata!$A$1:$P$1,0),FALSE) -> 3.2695143 | I10: =VLOOKUP($B10&$C$1,data_stata!$A:$P,MATCH(Scoreboard!I$1,data_stata!$A$1:$P$1,0),FALSE) -> -8.8485165 | J10: =VLOOKUP($B10&$C$1,data_stata!$A:$P,MATCH(Scoreboard!J$1,data_stata!$A$1:$P$1,0),FALSE) -> 3.1121044 | K10: =VLOOKUP($B10&$C$1,data_stata!$A:$P,MATCH(Scoreboard!K$1,data_stata!$A$1:$P$1,0),FALSE) -> 0 | ... N10: =VLOOKUP($B10&$C$1,data_stata!$A:$P,MATCH(Scoreboard!N$1,data_stata!$A$1:$P$1,0),FALSE) -> -0.71865797
B11: ES | C11: Spain | D11: =VLOOKUP($B11&$C$1,data_stata!$A:$P,MATCH(Scoreboard!D$1,data_stata!$A$1:$P$1,0),FALSE) -> -0.73579788 | E11: =VLOOKUP($B11&$C$1,data_stata!$A:$P,MATCH(Scoreboard!E$1,data_stata!$A$1:$P$1,0),FALSE) -> 0.58543235 | F11: =VLOOKUP($B11&$C$1,data_stata!$A:$P,MATCH(Scoreboard!F$1,data_stata!$A$1:$P$1,0),FALSE) -> 0.63626051 | G11: =VLOOKUP($B11&$C$1,data_stata!$A:$P,MATCH(Scoreboard!G$1,data_stata!$A$1:$P$1,0),FALSE) -> -0.014242012 | H11: =VLOOKUP($B11&$C$1,data_stata!$A:$P,MATCH(Scoreboard!H$1,data_stata!$A$1:$P$1,0),FALSE) -> -10.800853 | I11: =VLOOKUP($B11&$C$1,data_stata!$A:$P,MATCH(Scoreboard!I$1,data_stata!$A$1:$P$1,0),FALSE) -> -13.734506 | J11: =VLOOKUP($B11&$C$1,data_stata!$A:$P,MATCH(Scoreboard!J$1,data_stata!$A$1:$P$1,0),FALSE) -> -3.1441481 | K11: =VLOOKUP($B11&$C$1,data_stata!$A:$P,MATCH(Scoreboard!K$1,data_stata!$A$1:$P$1,0),FALSE) -> 91.983093 | ... N11: =VLOOKUP($B11&$C$1,data_stata!$A:$P,MATCH(Scoreboard!N$1,data_stata!$A$1:$P$1,0),FALSE) -> 0.15030575
B12: FI | C12: Finland | D12: =VLOOKUP($B12&$C$1,data_stata!$A:$P,MATCH(Scoreboard!D$1,data_stata!$A$1:$P$1,0),FALSE) -> -0.020896912 | E12: =VLOOKUP($B12&$C$1,data_stata!$A:$P,MATCH(Scoreboard!E$1,data_stata!$A$1:$P$1,0),FALSE) -> -1.0590265 | F12: =VLOOKUP($B12&$C$1,data_stata!$A:$P,MATCH(Scoreboard!F$1,data_stata!$A$1:$P$1,0),FALSE) -> 0.096578471 | G12: =VLOOKUP($B12&$C$1,data_stata!$A:$P,MATCH(Scoreboard!G$1,data_stata!$A$1:$P$1,0),FALSE) -> -0.11511082 | H12: =VLOOKUP($B12&$C$1,data_stata!$A:$P,MATCH(Scoreboard!H$1,data_stata!$A$1:$P$1,0),FALSE) -> -7.1361656 | I12: =VLOOKUP($B12&$C$1,data_stata!$A:$P,MATCH(Scoreboard!I$1,data_stata!$A$1:$P$1,0),FALSE) -> -19.918562 | J12: =VLOOKUP($B12&$C$1,data_stata!$A:$P,MATCH(Scoreboard!J$1,data_stata!$A$1:$P$1,0),FALSE) -> 0.9790653 | K12: =VLOOKUP($B12&$C$1,data_stata!$A:$P,MATCH(Scoreboard!K$1,data_stata!$A$1:$P$1,0),FALSE) -> 119.13233 | ... N12: =VLOOKUP($B12&$C$1,data_stata!$A:$P,MATCH(Scoreboard!N$1,data_stata!$A$1:$P$1,0),FALSE) -> -0.25097179
B13: FR | C13: France | D13: =VLOOKUP($B13&$C$1,data_stata!$A:$P,MATCH(Scoreboard!D$1,data_stata!$A$1:$P$1,0),FALSE) -> 3.6133308 | E13: =VLOOKUP($B13&$C$1,data_stata!$A:$P,MATCH(Scoreboard!E$1,data_stata!$A$1:$P$1,0),FALSE) -> 2.7984676 | F13: =VLOOKUP($B13&$C$1,data_stata!$A:$P,MATCH(Scoreboard!F$1,data_stata!$A$1:$P$1,0),FALSE) -> 0.24822722 | G13: =VLOOKUP($B13&$C$1,data_stata!$A:$P,MATCH(Scoreboard!G$1,data_stata!$A$1:$P$1,0),FALSE) -> -0.0051082121 | H13: =VLOOKUP($B13&$C$1,data_stata!$A:$P,MATCH(Scoreboard!H$1,data_stata!$A$1:$P$1,0),FALSE) -> 1.8165748 | I13: =VLOOKUP($B13&$C$1,data_stata!$A:$P,MATCH(Scoreboard!I$1,data_stata!$A$1:$P$1,0),FALSE) -> 3.1520116 | J13: =VLOOKUP($B13&$C$1,data_stata!$A:$P,MATCH(Scoreboard!J$1,data_stata!$A$1:$P$1,0),FALSE) -> 4.4464355 | K13: =VLOOKUP($B13&$C$1,data_stata!$A:$P,MATCH(Scoreboard!K$1,data_stata!$A$1:$P$1,0),FALSE) -> 103.49734 | ... N13: =VLOOKUP($B13&$C$1,data_stata!$A:$P,MATCH(Scoreboard!N$1,data_stata!$A$1:$P$1,0),FALSE) -> 0.37966824
B14: GR | C14: Greece | D14: =VLOOKUP($B14&$C$1,data_stata!$A:$P,MATCH(Scoreboard!D$1,data_stata!$A$1:$P$1,0),FALSE) -> -11.549681 | E14: =VLOOKUP($B14&$C$1,data_stata!$A:$P,MATCH(Scoreboard!E$1,data_stata!$A$1:$P$1,0),FALSE) -> 2.405977 | F14: =VLOOKUP($B14&$C$1,data_stata!$A:$P,MATCH(Scoreboard!F$1,data_stata!$A$1:$P$1,0),FALSE) -> -7.7358937 | G14: =VLOOKUP($B14&$C$1,data_stata!$A:$P,MATCH(Scoreboard!G$1,data_stata!$A$1:$P$1,0),FALSE) -> 0.056762572 | H14: =VLOOKUP($B14&$C$1,data_stata!$A:$P,MATCH(Scoreboard!H$1,data_stata!$A$1:$P$1,0),FALSE) -> -42.934139 | I14: =VLOOKUP($B14&$C$1,data_stata!$A:$P,MATCH(Scoreboard!I$1,data_stata!$A$1:$P$1,0),FALSE) -> -19.774176 | J14: =VLOOKUP($B14&$C$1,data_stata!$A:$P,MATCH(Scoreboard!J$1,data_stata!$A$1:$P$1,0),FALSE) -> -16.154646 | K14: =VLOOKUP($B14&$C$1,data_stata!$A:$P,MATCH(Scoreboard!K$1,data_stata!$A$1:$P$1,0),FALSE) -> 0 | ... N14: =VLOOKUP($B14&$C$1,data_stata!$A:$P,MATCH(Scoreboard!N$1,data_stata!$A$1:$P$1,0),FALSE) -> 0
B15: IE | C15: Ireland | D15: =VLOOKUP($B15&$C$1,data_stata!$A:$P,MATCH(Scoreboard!D$1,data_stata!$A$1:$P$1,0),FALSE) -> -4.6886559 | E15: =VLOOKUP($B15&$C$1,data_stata!$A:$P,MATCH(Scoreboard!E$1,data_stata!$A$1:$P$1,0),FALSE) -> 0 | F15: =VLOOKUP($B15&$C$1,data_stata!$A:$P,MATCH(Scoreboard!F$1,data_stata!$A$1:$P$1,0),FALSE) -> 13.715785 | G15: =VLOOKUP($B15&$C$1,data_stata!$A:$P,MATCH(Scoreboard!G$1,data_stata!$A$1:$P$1,0),FALSE) -> 0.24756618 | H15: =VLOOKUP($B15&$C$1,data_stata!$A:$P,MATCH(Scoreboard!H$1,data_stata!$A$1:$P$1,0),FALSE) -> -9.9307671 | I15: =VLOOKUP($B15&$C$1,data_stata!$A:$P,MATCH(Scoreboard!I$1,data_stata!$A$1:$P$1,0),FALSE) -> 0 | J15: =VLOOKUP($B15&$C$1,data_stata!$A:$P,MATCH(Scoreboard!J$1,data_stata!$A$1:$P$1,0),FALSE) -> 2.0619581 | K15: =VLOOKUP($B15&$C$1,data_stata!$A:$P,MATCH(Scoreboard!K$1,data_stata!$A$1:$P$1,0),FALSE) -> 99.915932 | ... N15: =VLOOKUP($B15&$C$1,data_stata!$A:$P,MATCH(Scoreboard!N$1,data_stata!$A$1:$P$1,0),FALSE) -> 0
B16: IT | C16: Italy | D16: =VLOOKUP($B16&$C$1,data_stata!$A:$P,MATCH(Scoreboard!D$1,data_stata!$A$1:$P$1,0),FALSE) -> -2.9806671 | E16: =VLOOKUP($B16&$C$1,data_stata!$A:$P,MATCH(Scoreboard!E$1,data_stata!$A$1:$P$1,0),FALSE) -> -2.5355794 | F16: =VLOOKUP($B16&$C$1,data_stata!$A:$P,MATCH(Scoreboard!F$1,data_stata!$A$1:$P$1,0),FALSE) -> 1.6857507 | G16: =VLOOKUP($B16&$C$1,data_stata!$A:$P,MATCH(Scoreboard!G$1,data_stata!$A$1:$P$1,0),FALSE) -> 0.69603682 | H16: =VLOOKUP($B16&$C$1,data_stata!$A:$P,MATCH(Scoreboard!H$1,data_stata!$A$1:$P$1,0),FALSE) -> -13.272143 | I16: =VLOOKUP($B16&$C$1,data_stata!$A:$P,MATCH(Scoreboard!I$1,data_stata!$A$1:$P$1,0),FALSE) -> -12.979579 | J16: =VLOOKUP($B16&$C$1,data_stata!$A:$P,MATCH(Scoreboard!J$1,data_stata!$A$1:$P$1,0),FALSE) -> 0.62078929 | K16: =VLOOKUP($B16&$C$1,data_stata!$A:$P,MATCH(Scoreboard!K$1,data_stata!$A$1:$P$1,0),FALSE) -> 64.193703 | ... N16: =VLOOKUP($B16&$C$1,data_stata!$A:$P,MATCH(Scoreboard!N$1,data_stata!$A$1:$P$1,0),FALSE) -> -0.36835957
B17: LT | C17: Lithuania | D17: =VLOOKUP($B17&$C$1,data_stata!$A:$P,MATCH(Scoreboard!D$1,data_stata!$A$1:$P$1,0),FALSE) -> -0.45365524 | E17: =VLOOKUP($B17&$C$1,data_stata!$A:$P,MATCH(Scoreboard!E$1,data_stata!$A$1:$P$1,0),FALSE) -> -1.2021061 | F17: =VLOOKUP($B17&$C$1,data_stata!$A:$P,MATCH(Scoreboard!F$1,data_stata!$A$1:$P$1,0),FALSE) -> -1.3280824 | G17: =VLOOKUP($B17&$C$1,data_stata!$A:$P,MATCH(Scoreboard!G$1,data_stata!$A$1:$P$1,0),FALSE) -> -0.19418874 | H17: =VLOOKUP($B17&$C$1,data_stata!$A:$P,MATCH(Scoreboard!H$1,data_stata!$A$1:$P$1,0),FALSE) -> -2.2500827 | I17: =VLOOKUP($B17&$C$1,data_stata!$A:$P,MATCH(Scoreboard!I$1,data_stata!$A$1:$P$1,0),FALSE) -> -9.6022768 | J17: =VLOOKUP($B17&$C$1,data_stata!$A:$P,MATCH(Scoreboard!J$1,data_stata!$A$1:$P$1,0),FALSE) -> 4.387197 | K17: =VLOOKUP($B17&$C$1,data_stata!$A:$P,MATCH(Scoreboard!K$1,data_stata!$A$1:$P$1,0),FALSE) -> 0 | ... N17: =VLOOKUP($B17&$C$1,data_stata!$A:$P,MATCH(Scoreboard!N$1,data_stata!$A$1:$P$1,0),FALSE) -> -0.32414365
... B24: SK | C24: Slovakia | D24: =VLOOKUP($B24&$C$1,data_stata!$A:$P,MATCH(Scoreboard!D$1,data_stata!$A$1:$P$1,0),FALSE) -> 2.5827675 | E24: =VLOOKUP($B24&$C$1,data_stata!$A:$P,MATCH(Scoreboard!E$1,data_stata!$A$1:$P$1,0),FALSE) -> 0.71572202 | F24: =VLOOKUP($B24&$C$1,data_stata!$A:$P,MATCH(Scoreboard!F$1,data_stata!$A$1:$P$1,0),FALSE) -> -4.4924865 | G24: =VLOOKUP($B24&$C$1,data_stata!$A:$P,MATCH(Scoreboard!G$1,data_stata!$A$1:$P$1,0),FALSE) -> 0.049750801 | H24: =VLOOKUP($B24&$C$1,data_stata!$A:$P,MATCH(Scoreboard!H$1,data_stata!$A$1:$P$1,0),FALSE) -> 1.6372415 | I24: =VLOOKUP($B24&$C$1,data_stata!$A:$P,MATCH(Scoreboard!I$1,data_stata!$A$1:$P$1,0),FALSE) -> 4.6875467 | J24: =VLOOKUP($B24&$C$1,data_stata!$A:$P,MATCH(Scoreboard!J$1,data_stata!$A$1:$P$1,0),FALSE) -> 6.3524857 | K24: =VLOOKUP($B24&$C$1,data_stata!$A:$P,MATCH(Scoreboard!K$1,data_stata!$A$1:$P$1,0),FALSE) -> 0 | ... N24: =VLOOKUP($B24&$C$1,data_stata!$A:$P,MATCH(Scoreboard!N$1,data_stata!$A$1:$P$1,0),FALSE) -> -0.096666336
C25: T1 | D25: 0.22 | E25: 2 | F25: -0.8 | G25: 0 | H25: -1 | I25: -1 | J25: 3 | K25: 75 | L25: 0.5 | M25: 2.5 | N25: 0.1
C26: T2 | D26: 1.2 | E26: 4 | F26: -1.5 | G26: -0.1 | H26: 2 | I26: 2 | J26: 6 | K26: 85 | L26: 1.5 | M26: 5 | N26: 0.3
C27: T3 | D27: 2.2 | E27: 6 | F27: -2.3 | G27: -0.15 | H27: 4 | I27: 4 | J27: 9 | K27: 95 | L27: 2.5 | M27: 7.5 | N27: 0.6

Sheet data_stata
A1: vlookup | B1: country | C1: date | D1: year | E1: quarter | F1: C1 | G1: C2 | H1: C3 | I1: C4 | J1: C5 | K1: C6 | L1: C7 | M1: C8 | N1: C9 | O1: C10 | P1: C11
A2: AT1990Q1 | B2: AT | C2: 32874 | D2: 1990 | E2: 1
A3: AT1990Q2 | B3: AT | C3: 32964 | D3: 1990 | E3: 2
A4: AT1990Q3 | B4: AT | C4: 33055 | D4: 1990 | E4: 3
A5: AT1990Q4 | B5: AT | C5: 33147 | D5: 1990 | E5: 4 | H5: 0.81864119
A6: AT1991Q1 | B6: AT | C6: 33239 | D6: 1991 | E6: 1 | H6: 0.68294442
A7: AT1991Q2 | B7: AT | C7: 33329 | D7: 1991 | E7: 2 | H7: 0.34661633
A8: AT1991Q3 | B8: AT | C8: 33420 | D8: 1991 | E8: 3 | H8: 0.14919271
A9: AT1991Q4 | B9: AT | C9: 33512 | D9: 1991 | E9: 4 | H9: 0.080240846
A10: AT1992Q1 | B10: AT | C10: 33604 | D10: 1992 | E10: 1 | H10: 0.52500731
A11: AT1992Q2 | B11: AT | C11: 33695 | D11: 1992 | E11: 2 | H11: 0.71553504
A12: AT1992Q3 | B12: AT | C12: 33786 | D12: 1992 | E12: 3 | H12: 0.39748967
A13: AT1992Q4 | B13: AT | C13: 33878 | D13: 1992 | E13: 4 | H13: -0.0082018003
A14: AT1993Q1 | B14: AT | C14: 33970 | D14: 1993 | E14: 1 | H14: 0.098713584
A15: AT1993Q2 | B15: AT | C15: 34060 | D15: 1993 | E15: 2 | H15: -0.30184725
A16: AT1993Q3 | B16: AT | C16: 34151 | D16: 1993 | E16: 3 | H16: -0.24567407
... A37: AT1998Q4 | B37: AT | C37: 36069 | D37: 1998 | E37: 4 | H37: -1.8649193
A38: AT1999Q1 | B38: AT | C38: 36161 | D38: 1999 | E38: 1 | H38: -1.8447833 | N38: -9.666667
A39: AT1999Q2 | B39: AT | C39: 36251 | D39: 1999 | E39: 2 | H39: -2.0815983 | N39: -10.333333
A40: AT1999Q3 | B40: AT | C40: 36342 | D40: 1999 | E40: 3 | H40: -2.235343 | K40: -0.0013465876 | N40: -8.333333
A41: AT1999Q4 | B41: AT | C41: 36434 | D41: 1999 | E41: 4 | H41: -2.2609696 | K41: -0.89055997 | M41: 69.10791 | N41: -8
A42: AT2000Q1 | B42: AT | C42: 36526 | D42: 2000 | E42: 1 | H42: -1.7285872 | K42: 0.6846447 | M42: 70.107887 | N42: -10.666667
A43: AT2000Q2 | B43: AT | C43: 36617 | D43: 2000 | E43: 2 | H43: -1.3565158 | K43: 0.49886164 | M43: 70.899353 | N43: -10.333333
A44: AT2000Q3 | B44: AT | C44: 36708 | D44: 2000 | E44: 3 | H44: -0.94953936 | K44: 0.93549687 | L44: 5.2345719 | M44: 71.984131 | N44: -12
A45: AT2000Q4 | B45: AT | C45: 36800 | D45: 2000 | E45: 4 | H45: -0.70597112 | K45: -0.15554453 | L45: 5.6487966 | M45: 70.812813 | N45: -10.666667
A46: AT2001Q1 | B46: AT | C46: 36892 | D46: 2001 | E46: 1 | G46: 6.8678226 | H46: -0.82209283 | K46: -1.2931631 | L46: 8.0888634 | M46: 71.499138 | N46: -8
A47: AT2001Q2 | B47: AT | C47: 36982 | D47: 2001 | E47: 2 | G47: 5.7910275 | H47: -1.0768718 | K47: -1.432488 | L47: 8.7615471 | M47: 73.261139 | N47: -8
A48: AT2001Q3 | B48: AT | C48: 37073 | D48: 2001 | E48: 3 | G48: 5.3468804 | H48: -0.9566983 | K48: -0.88149387 | L48: 9.0723801 | M48: 74.946243 | N48: -7.3333335
A49: AT2001Q4 | B49: AT | C49: 37165 | D49: 2001 | E49: 4 | G49: 6.099185 | H49: -0.79628134 | K49: -1.0615997 | L49: 9.0237284 | M49: 72.243065 | N49: -7.3333335
A50: AT2002Q1 | B50: AT | C50: 37257 | D50: 2002 | E50: 1 | G50: 4.2707639 | H50: 0.23902133 | K50: -1.9261531 | L50: 9.9500847 | M50: 72.239693 | N50: -2
A51: AT2002Q2 | B51: AT | C51: 37347 | D51: 2002 | E51: 2 | G51: 3.3535182 | H51: 0.95137608 | K51: -1.8147695 | L51: 9.8006763 | M51: 72.621986 | N51: -2.3333333
A52: AT2002Q3 | B52: AT | C52: 37438 | D52: 2002 | E52: 3 | G52: 2.3107297 | H52: 1.5427232 | K52: -2.2131152 | L52: 10.090236 | M52: 73.553391 | N52: -0.33333334
A53: AT2002Q4 | B53: AT | C53: 37530 | D53: 2002 | E53: 4 | G53: 1.9482249 | H53: 2.1024523 | K53: -2.683042 | L53: 14.656445 | M53: 73.97506 | N53: -2
A54: AT2003Q1 | B54: AT | C54: 37622 | D54: 2003 | E54: 1 | G54: 2.4538388 | H54: 1.9896294 | K54: -2.049763 | L54: 14.24996 | M54: 74.538063 | N54: -0.66666669
A55: AT2003Q2 | B55: AT | C55: 37712 | D55: 2003 | E55: 2 | G55: 2.6291528 | H55: 1.9316751 | K55: -1.8919817 | L55: 13.223071 | M55: 74.589569 | N55: -0.66666669
A56: AT2003Q3 | B56: AT | C56: 37803 | D56: 2003 | E56: 3 | G56: 1.8092209 | H56: 1.5903239 | J56: 0.020598086 | K56: -2.2710526 | L56: 14.260579 | M56: 74.28933 | N56: -0.66666669
A57: AT2003Q4 | B57: AT | C57: 37895 | D57: 2003 | E57: 4 | G57: 2.1717241 | H57: 1.5483316 | J57: -0.16292632 | K57: -0.92385226 | L57: 14.771158 | M57: 74.132782 | N57: -0.33333334
A58: AT2004Q1 | B58: AT | C58: 37987 | D58: 2004 | E58: 1 | G58: 2.478435 | H58: 1.8408493 | J58: -0.461777 | K58: -0.85936618 | L58: 13.056804 | M58: 74.677338 | N58: -4
A59: AT2004Q2 | B59: AT | C59: 38078 | D59: 2004 | E59: 2 | G59: 2.9139874 | H59: 2.2653456 | J59: 0.22162178 | K59: -0.16242951 | L59: 17.727102 | M59: 75.894257 | N59: -1
A60: AT2004Q3 | B60: AT | C60: 38169 | D60: 2004 | E60: 3 | G60: 3.1899488 | H60: 2.2850723 | J60: -0.21952626 | K60: -0.47200689 | L60: 17.467989 | M60: 76.46373 | N60: -2
A61: AT2004Q4 | B61: AT | C61: 38261 | D61: 2004 | E61: 4 | G61: 1.9657562 | H61: 2.0759382 | J61: -0.34354028 | K61: -4.6918297 | L61: 17.988884 | M61: 76.176819 | N61: -0.66666669
A62: AT2005Q1 | B62: AT | C62: 38353 | D62: 2005 | E62: 1 | F62: 0.2523613 | G62: 2.3764417 | H62: 2.1145754 | I62: -0.35019624 | J62: -0.31115961 | K62: -2.8506351 | L62: 17.660324 | M62: 76.066864 | N62: -1.3333334 | P62: -0.5005331
A63: AT2005Q2 | B63: AT | C63: 38443 | D63: 2005 | E63: 2 | F63: 2.9861526 | G63: 2.7482109 | H63: 1.8584638 | I63: -0.23667513 | J63: 3.6315324 | K63: -2.4516678 | L63: 19.995443 | M63: 76.191475 | N63: -1.6666666 | P63: -0.3493576
A64: AT2005Q3 | B64: AT | C64: 38534 | D64: 2005 | E64: 3 | F64: 3.2011909 | G64: 3.4611757 | H64: 1.7148921 | I64: -0.20028959 | J64: 2.9142687 | K64: -1.7310965 | L64: 19.674244 | M64: 77.202126 | N64: -3 | P64: -0.19472218
A65: AT2005Q4 | B65: AT | C65: 38626 | D65: 2005 | E65: 4 | F65: 3.2878876 | G65: 3.702214 | H65: 2.258388 | I65: -0.19845973 | J65: 1.7490873 | K65: -0.66355062 | L65: 14.765163 | M65: 81.711189 | N65: -1.3333334 | P65: -0.12880802
A66: AT2006Q1 | B66: AT | C66: 38718 | D66: 2006 | E66: 1 | F66: 3.3141327 | G66: 2.7810366 | H66: 2.4579704 | I66: -0.12362948 | J66: 0.36866015 | K66: -4.059021 | L66: 14.613344 | M66: 82.628532 | N66: -1.3333334 | P66: -0.27338219
A67: AT2006Q2 | B67: AT | C67: 38808 | D67: 2006 | E67: 2 | F67: 3.305603 | G67: 3.0820897 | H67: 2.6661291 | I67: -0.16450475 | J67: 0.54180628 | K67: -2.0024085 | L67: 15.16522 | M67: 83.915787 | N67: -0.66666669 | P67: -0.13680935
A68: AT2006Q3 | B68: AT | C68: 38899 | D68: 2006 | E68: 3 | F68: 3.6730614 | G68: 3.5293546 | H68: 2.736779 | I68: -0.097386435 | J68: 0.10734323 | K68: -1.1281328 | L68: 13.205209 | M68: 84.319046 | N68: -0.66666669 | P68: 0.018491745
A69: AT2006Q4 | B69: AT | C69: 38991 | D69: 2006 | E69: 4 | F69: 3.2470627 | G69: 5.3575649 | H69: 3.2946954 | I69: -0.13355753 | J69: -1.2855672 | K69: -1.7692645 | L69: 15.669695 | M69: 83.095009 | N69: -1.6666666 | P69: 0.31558895
A70: AT2007Q1 | B70: AT | C70: 39083 | D70: 2007 | E70: 1 | F70: 2.7227783 | G70: 4.464395 | H70: 3.5530663 | I70: -0.076536968 | J70: -2.3951843 | K70: -2.7661812 | L70: 15.381185 | M70: 84.073509 | N70: 1.6666666 | P70: 0.21509743
A71: AT2007Q2 | B71: AT | C71: 39173 | D71: 2007 | E71: 2 | F71: -0.14464569 | G71: 4.7918534 | H71: 3.8350058 | I71: -0.12759393 | J71: -2.2325432 | K71: -1.0467681 | L71: 10.337507 | M71: 82.646599 | N71: 0.33333334 | P71: 0.37783432
A72: AT2007Q3 | B72: AT | C72: 39264 | D72: 2007 | E72: 3 | F72: -0.64209366 | G72: 4.9519553 | H72: 3.9583199 | I72: -0.10588035 | J72: -2.2297814 | K72: -0.495599 | L72: 10.273114 | M72: 82.43354 | N72: 0.33333334 | P72: 0.5624876
A73: AT2007Q4 | B73: AT | C73: 39356 | D73: 2007 | E73: 4 | F73: -0.93501663 | G73: 4.8712668 | H73: 3.8024075 | I73: -0.12000385 | J73: -2.6019518 | K73: 1.0597092 | L73: 9.5333624 | M73: 82.840096 | N73: -0.66666669 | P73: 0.62540436
... A93: AT2012Q4 | B93: AT | C93: 41183 | D93: 2012 | E93: 4 | F93: -1.9877129 | G93: -0.47170329 | H93: 1.4828039 | I93: 0.074136637 | J93: -4.0686793 | K93: -4.1947207 | L93: 2.6454656 | M93: 84.184937 | N93: 5.3333335 | P93: -0.54874134
A94: AT2013Q1 | B94: AT | C94: 41275 | D94: 2013 | E94: 1 | F94: -1.2679367 | G94: 0.12642878 | H94: 1.8930453 | I94: 0.10016022 | J94: -4.3618641 | K94: -4.337677 | L94: 1.9849144 | M94: 83.554016 | N94: 4.3333335 | O94: 4.1362658 | P94: -0.43821716
A95: AT2013Q2 | B95: AT | C95: 41365 | D95: 2013 | E95: 2 | F95: -1.7272644 | G95: -0.28915083 | H95: 2.0829115 | I95: 0.1088959 | J95: -4.5669465 | K95: -5.1461196 | L95: 0.73573852 | M95: 83.725327 | N95: 5 | O95: 3.5162776 | P95: -0.52657557
A96: AT2013Q3 | B96: AT | C96: 41456 | D96: 2013 | E96: 3 | F96: -1.5651054 | G96: -0.35104224 | H96: 2.0481689 | I96: 0.13654846 | J96: -4.2462621 | K96: -4.9783564 | L96: 0.95138264 | M96: 84.814842 | N96: 5.6666665 | O96: 3.8338094 | P96: -0.61695385
A97: AT2013Q4 | B97: AT | C97: 41548 | D97: 2013 | E97: 4 | F97: -1.7151108 | G97: 1.0431727 | H97: 1.9431312 | I97: 0.18630461 | J97: -4.7848234 | K97: 0.065605335 | L97: 0.32665047 | M97: 83.989128 | N97: 5 | O97: 2.6404867 | P97: -0.42100859
A98: AT2014Q1 | B98: AT | C98: 41640 | D98: 2014 | E98: 1 | F98: -1.6564827 | G98: 1.0929414 | H98: 1.3758307 | I98: 0.23197055 | J98: -4.9782043 | K98: -0.85270721 | L98: 1.2231205 | M98: 84.12674 | N98: 5 | O98: 3.869822 | P98: -0.29856062
A99: AT2014Q2 | B99: AT | C99: 41730 | D99: 2014 | E99: 2 | F99: -1.7603111 | G99: 1.1043882 | H99: 1.2106969 | I99: 0.18158144 | J99: -4.9314985 | K99: -0.75291163 | L99: 0.53463358 | M99: 84.386406 | N99: 7 | O99: 3.7671249 | P99: -0.18737555
A100: AT2014Q3 | B100: AT | C100: 41821 | D100: 2014 | E100: 3 | F100: -1.7042465 | G100: 1.4410543 | H100: 1.3719743 | I100: 0.089093797 | J100: -4.4290156 | K100: -0.77725446 | L100: 0.63247222 | M100: 84.18354 | N100: 4.6666665 | O100: 2.7874231 | P100: -0.13258791
A101: AT2014Q4 | B101: AT | C101: 41913 | D101: 2014 | E101: 4 | F101: -2.9223595 | G101: 0.69496614 | H101: 2.47399 | I101: 0.069104329 | J101: -7.5446353 | K101: -6.2624049 | L101: 0.66642421 | M101: 83.700172 | N101: 5 | O101: 2.858741 | P101: -0.20337963
A102: AT2015Q1 | B102: AT | C102: 42005 | D102: 2015 | E102: 1 | F102: -2.4899826 | G102: 2.1423769 | H102: 3.0069957 | I102: 0.20209625 | J102: -6.6987748 | K102: -4.1402235 | L102: 1.9672067 | M102: 85.205154 | N102: 4.6666665 | O102: 1.5969125 | P102: -0.1028657
A103: AT2015Q2 | B103: AT | C103: 42095 | D103: 2015 | E103: 2 | F103: -2.6448174 | G103: 1.8758103 | H103: 3.0790856 | I103: 0.0072772168 | J103: -6.937427 | K103: -5.4572587 | L103: 1.9043279 | M103: 84.819817 | N103: 4.3333335 | O103: 3.2568922 | P103: -0.17741108
A104: AT2015Q3 | B104: AT | C104: 42186 | D104: 2015 | E104: 3 | F104: -2.7482071 | G104: 2.1806686 | H104: 2.9342644 | I104: 0.026523218 | J104: -6.546423 | K104: -5.2017994 | L104: 2.1271102 | M104: 84.860611 | N104: 3.6666667 | O104: 3.9107261 | P104: -0.19761276
A105: AT2015Q4 | B105: AT | C105: 42278 | D105: 2015 | E105: 4 | F105: -2.7167511 | G105: 0.1221012 | H105: 1.7253938 | I105: 0.055442564 | J105: -6.7763886 | K105: -7.1375842 | L105: 2.783762 | M105: 85.14402 | N105: 4.6666665 | O105: 3.6388545 | P105: -0.4587574
... A130: AT2022Q1 | B130: AT | C130: 44562 | D130: 2022 | E130: 1 | F130: 2.4189949 | G130: 0.82022309 | H130: -0.0079380581 | I130: 0.041655581 | J130: 3.7858102 | K130: 0.0011330439 | L130: 3.7871227 | M130: 86.340889 | N130: 10 | O130: 7.6865516 | P130: 0.10050106
A131: AT2022Q2 | B131: AT | C131: 44652 | D131: 2022 | E131: 2 | F131: 0.53263474 | I131: 0.025652604 | J131: 3.0873265 | L131: 3.1136074
A132: BE1990Q1 | B132: BE | C132: 32874 | D132: 1990 | E132: 1
A133: BE1990Q2 | B133: BE | C133: 32964 | D133: 1990 | E133: 2
A134: BE1990Q3 | B134: BE | C134: 33055 | D134: 1990 | E134: 3
A135: BE1990Q4 | B135: BE | C135: 33147 | D135: 1990 | E135: 4
A136: BE1991Q1 | B136: BE | C136: 33239 | D136: 1991 | E136: 1
A137: BE1991Q2 | B137: BE | C137: 33329 | D137: 1991 | E137: 2
A138: BE1991Q3 | B138: BE | C138: 33420 | D138: 1991 | E138: 3
A139: BE1991Q4 | B139: BE | C139: 33512 | D139: 1991 | E139: 4
A140: BE1992Q1 | B140: BE | C140: 33604 | D140: 1992 | E140: 1
A141: BE1992Q2 | B141: BE | C141: 33695 | D141: 1992 | E141: 2
A142: BE1992Q3 | B142: BE | C142: 33786 | D142: 1992 | E142: 3
A143: BE1992Q4 | B143: BE | C143: 33878 | D143: 1992 | E143: 4
... A169: BE1999Q2 | B169: BE | C169: 36251 | D169: 1999 | E169: 2
A170: BE1999Q3 | B170: BE | C170: 36342 | D170: 1999 | E170: 3 | K170: -0.25900766
A171: BE1999Q4 | B171: BE | C171: 36434 | D171: 1999 | E171: 4 | K171: 0.76057214 | M171: 66.978096
A172: BE2000Q1 | B172: BE | C172: 36526 | D172: 2000 | E172: 1 | K172: -0.40269774 | M172: 67.296257
A173: BE2000Q2 | B173: BE | C173: 36617 | D173: 2000 | E173: 2 | K173: -0.46694231 | M173: 66.336617
A174: BE2000Q3 | B174: BE | C174: 36708 | D174: 2000 | E174: 3 | K174: -1.7635977 | L174: 6.831346 | M174: 65.693069
A175: BE2000Q4 | B175: BE | C175: 36800 | D175: 2000 | E175: 4 | H175: 4.1770878 | K175: 2.5864592 | L175: 7.924839 | M175: 65.468262
A176: BE2001Q1 | B176: BE | C176: 36892 | D176: 2001 | E176: 1 | G176: 8.6691246 | H176: 4.0008483 | K176: -1.3404371 | L176: 7.8182092 | M176: 64.460403
A177: BE2001Q2 | B177: BE | C177: 36982 | D177: 2001 | E177: 2 | G177: 7.9297338 | H177: 3.3148601 | K177: -0.13072841 | L177: 6.8909025 | M177: 64.098557
A178: BE2001Q3 | B178: BE | C178: 37073 | D178: 2001 | E178: 3 | G178: 6.697258 | H178: 3.5521839 | K178: -2.9954164 | L178: 6.3321543 | M178: 61.789253
A179: BE2001Q4 | B179: BE | C179: 37165 | D179: 2001 | E179: 4 | G179: 6.7402844 | H179: 3.5279961 | K179: 1.5281426 | L179: 6.8879213 | M179: 61.642929
A180: BE2002Q1 | B180: BE | C180: 37257 | D180: 2002 | E180: 1 | G180: 5.7862186 | H180: 4.0228786 | K180: -1.337706 | L180: 6.4856067 | M180: 60.853596
A181: BE2002Q2 | B181: BE | C181: 37347 | D181: 2002 | E181: 2 | G181: 5.1096048 | H181: 4.7689695 | K181: -2.5104098 | L181: 5.5540624 | M181: 61.81036
A182: BE2002Q3 | B182: BE | C182: 37438 | D182: 2002 | E182: 3 | G182: 4.6952848 | H182: 4.4603548 | K182: -5.1075015 | L182: 4.7375188 | M182: 62.023449
A183: BE2002Q4 | B183: BE | C183: 37530 | D183: 2002 | E183: 4 | G183: 3.0462813 | H183: 4.5855327 | K183: -3.273634 | L183: 5.1504002 | M183: 63.325321
A184: BE2003Q1 | B184: BE | C184: 37622 | D184: 2003 | E184: 1 | G184: 2.3462608 | H184: 3.6154439 | K184: -6.1904817 | L184: 6.1701689 | M184: 63.435284
A185: BE2003Q2 | B185: BE | C185: 37712 | D185: 2003 | E185: 2 | G185: 2.7252469 | H185: 4.5181837 | K185: -3.9972908 | L185: 6.9731884 | M185: 64.186241
A186: BE2003Q3 | B186: BE | C186: 37803 | D186: 2003 | E186: 3 | G186: 3.2737257 | H186: 3.8113251 | J186: -0.31237715 | K186: -4.1191225 | L186: 7.0352612 | M186: 63.643867
A187: BE2003Q4 | B187: BE | C187: 37895 | D187: 2003 | E187: 4 | G187: 2.9981301 | H187: 3.5465734 | J187: -0.20801696 | K187: 0.37636134 | L187: 6.5729213 | M187: 64.460762
A188: BE2004Q1 | B188: BE | C188: 37987 | D188: 2004 | E188: 1 | G188: 3.3769748 | H188: 3.7480416 | J188: -0.067213617 | K188: -1.8481503 | L188: 7.6531997 | M188: 65.289497
...

Sheet Metadata
C1: MPR Cyclical Scoreboard
B2: Code | C2: Indicator (untransformed) | D2: Data provider | E2: Dataset
A3: C2 | B3: CTN3R | C3: Total credit (unconsolidated - including trade credit), deflated by CPIP | D3: SDW | E3: QSA, BISM, IEAQ, ICP, MEI
A4: C1 | B4: CBNFA_GDP | C4: Bank credit to NFPS (adjusted by securitisation) to GDP | D4: SDW | E4: BSI, BISM, MNA, ESA
A5: C9 | B5: RRE_HPI_B | C5: Nominal House price-to-income | D5: ECB - DG-E / OECD /SDW | E5: RPV
A6: C3 | B6: CA2GDPEUR | C6: Current account balance to GDP | D6: SDW | E6: BP6, ST1, OEO, MNA, ESA
A7: C11 | B7: DSR | C7: Debt service ratio | D7: SDW/ BIS | E7: QSA, MIR, BSI, MNA
A8: C4 | B8: NLS | C8: Spreads new lending private non-financial sector | D8: SDW | E8: RAI
B10: Methodology: | C10: 2018-05-23 Item 2 MPR technical appendix | D10: MPR
C11: CRAR | D11: CRAR
B13: Code | C13: Underlying indicators | D13: Original frequency | E13: Aggregation method/ observations | F13: Unit | G13: Data provider | H13: Dataset | I13: SDW code | J13: Available in dd-mm-yy (quarter available)
B14: C1 - Bank credit-to-GDP ratio, 2-year av. change | C14: CBNFA: Bank credit to NFPS - adjusted by securitisation (=A+B+C+D)
C15: A: Loans to NFCs - adjusted by securitization | D15: M | E15: end of quarter values | F15: Millions of Euros | G15: SDW | H15: BSI | I15: BSI.M.PT.N.A.A20T.A.1.U6.2240.Z01.E
C16: B: Loans to HHs - adjusted by securitization | D16: M | E16: end of quarter values | F16: Millions of Euros | G16: SDW | H16: BSI | I16: BSI.M.PT.N.A.A20T.A.1.U6.2250.Z01.E
C17: C: Debt securities of NFC | D17: Q | F17: Millions of Euros | G17: SDW | H17: BSI | I17: BSI.Q.PT.N.A.A30.A.1.U6.2240.Z01.E
C18: D: Debt securities of HHs | D18: Q | F18: Millions of Euros | G18: SDW | H18: BSI | I18: BSI.Q.PT.N.A.A30.A.1.U6.2250.Z01.E
C19: Loans + debt securities to nonfin private sector - longer time series | D19: Q | E19: used for backasting* | G19: BIS | I19: https://www.bis.org/statistics/totcredit.htm
C20: GDPN: Gross domestic product, nominal
C21: Gross domestic product, nominal | D21: Q | F21: Millions of Euros | G21: SDW | H21: MNA | I21: MNA.Q.Y.PT.W2.S1.S1.B.B1GQ._Z._Z._Z.XDC.V.N
C22: Gross domestic product, nominal - longer time series | D22: Q | E22: merged with main series for backasting (earlier dates using ECB values since no Haver access) | G22: Haver | H22: Haver | I22: A???GDP@OECDNAQ
B23: C2 - Real total credit, 2-year av. growth | C23: CTHHN: Total credit to HHs (=A+B)
C24: A: QSA loans to HHs, NSA mil. local currency | D24: Q | F24: Millions of Euros | G24: SDW | H24: QSA | I24: QSA.Q.N.PT.W0.S1M.S1.N.L.LE.F4.T._Z.XDC._T.S.V.N._T
C25: B: QSA debt sec issued by HHs, NSA mil. local currency | D25: Q | F25: Millions of Euros | G25: SDW | H25: QSA | I25: QSA.Q.N.PT.W0.S1M.S1.N.L.LE.F3.T._Z.XDC._T.S.V.N._T
C26: Total credit to HHs, longer time series | D26: Q | E26: used for backasting* | G26: SDW | H26: QSA
C27: CTNFCN3: Total credit to NFCs - unconsolidated (including trade credit) (=A+B+C)
C28: A: Total loans to NFCs, NSA mil. local currency | D28: Q | F28: Millions of Euros | G28: SDW | H28: QSA | I28: QSA.Q.N.PT.W0.S11.S1.N.L.LE.F4.T._Z.XDC._T.S.V.N._T
C29: B: Total debt securities issued by NFCs, NSA mil. local currency | D29: Q | F29: Millions of Euros | G29: SDW | H29: QSA | I29: QSA.Q.N.PT.W0.S11.S1.N.L.LE.F3.T._Z.XDC._T.S.V.N._T
C30: C: Total trade credit granted to NFCs, NSA mil. local currency | D30: Q | F30: Millions of Euros | G30: SDW | H30: QSA | I30: QSA.Q.N.PT.W0.S11.S1.N.L.LE.F81.T._Z.XDC._T.S.V.N._T
C31: Total credit to NFC, longer time series | D31: Q | E31: used for backasting* | G31: SDW
C32: CPI
C33: HICP, SA 2015 = 100 | D33: M | E33: average over period | F33: index 2015 = 100 | G33: SDW | H33: ICP | I33: ICP.M.PT.Y.000000.3.INX | J33: 17 working days after the end of the reference month
C34: HICP SA long series, 2010 = 100 | D34: Q | E34: used for backasting* | F34: index 2015 = 100 - rebased | G34: SDW-OECD | H34: MEI | I34: MEI.Q.PT.CPALTT01.IXOB
B35: C3 - Current account balance, % of GDP | C35: CA2GDPEUR: Current account balance to GDP (4Q mov SUM A / 4Q mov SUM B)
C36: Current account (A) | D36: Q | F36: Millions of Euros | G36: SDW | H36: BP6 | I36: BP6.Q.N.PT.W1.S1.S1.T.B.CA._Z._Z._Z.EUR._T._X.N
C37: Current account, long time series | D37: A | E37: used for backasting* / interpolation with annual values | F37: Euros | G37: SDW-OECD | H37: OEO (ecoconomic outlook of OECD) | I37: OEO.Q.PRT.CB
C38: GDPN: Nominal Gross Domestic Product
C39: Nominal Gross Domestic Product (B) | D39: Q | F39: Millions of Euros | G39: SDW | H39: MNA | I39: MNA.Q.N.PT.W2.S1.S1.B.B1GQ._Z._Z._Z.EUR.V.N
D40: A | E40: used for backasting* / interpolation with annual values | F40: Euros | G40: SDW-OECD | H40: OEO (ecoconomic outlook of OECD) | I40: OEO.Q.PT.GDP
B41: C4 - NFPS lending spreads, 2-year av. change | C41: NLS: Spreads new lending private non-financial sector | D41: M | E41: end of quarter values | F41: Percentage points | G41: SDW | H41: RAI | I41: RAI.M.PT.LMGBLNFCH.EUR.MIR.Z
B42: C5 - Bank credit-to-GDP gap | C42: CBNFA: Bank credit to NFPS - adjusted by securitisation (=A+B+C+D)
C43: A: Loans to NFCs - adjusted by securitization | D43: M | E43: end of quarter values | F43: Millions of Euros | G43: SDW | H43: BSI | I43: BSI.M.PT.N.A.A20T.A.1.U6.2240.Z01.E
C44: B: Loans to HHs - adjusted by securitization | D44: M | E44: end of quarter values | F44: Millions of Euros | G44: SDW | H44: BSI | I44: BSI.M.PT.N.A.A20T.A.1.U6.2250.Z01.E
C45: C: Debt securities of NFC | D45: Q | F45: Millions of Euros | G45: SDW | H45: BSI | I45: BSI.Q.PT.N.A.A30.A.1.U6.2240.Z01.E
C46: D: Debt securities of HHs | D46: Q | F46: Millions of Euros | G46: SDW | H46: BSI | I46: BSI.Q.PT.N.A.A30.A.1.U6.2250.Z01.E
C47: Loans + debt securities to nonfin private sector - longer time series | D47: Q | E47: used for backasting* | G47: BIS | I47: https://www.bis.org/statistics/totcredit.htm
C48: GDPN: Gross domestic product, nominal
C49: Gross domestic product, nominal | D49: Q | F49: Millions of Euros | G49: SDW | H49: MNA | I49: MNA.Q.Y.PT.W2.S1.S1.B.B1GQ._Z._Z._Z.XDC.V.N
C50: Gross domestic product, nominal - longer time series | D50: Q | E50: merged with main series for backasting (earlier dates using ECB values since no Haver access) | G50: Haver | H50: Haver | I50: A???GDP@OECDNAQ
B51: C6 - Total credit-to-GDP gap | C51: CTHHN: Total credit to HHs (=A+B)
C52: A: QSA loans to HHs, NSA mil. local currency | D52: Q | F52: Millions of Euros | G52: SDW | H52: QSA | I52: QSA.Q.N.PT.W0.S1M.S1.N.L.LE.F4.T._Z.XDC._T.S.V.N._T
C53: B: QSA debt sec issued by HHs, NSA mil. local currency | D53: Q | F53: Millions of Euros | G53: SDW | H53: QSA | I53: QSA.Q.N.PT.W0.S1M.S1.N.L.LE.F3.T._Z.XDC._T.S.V.N._T
C54: Total credit to HHs, longer time series | D54: Q | E54: used for backasting* | G54: SDW | H54: QSA
C55: CTNFCN3: Total credit to NFCs - unconsolidated (including trade credit) (=A+B+C)
C56: A: Total loans to NFCs, NSA mil. local currency | D56: Q | F56: Millions of Euros | G56: SDW | H56: QSA | I56: QSA.Q.N.PT.W0.S11.S1.N.L.LE.F4.T._Z.XDC._T.S.V.N._T
C57: B: Total debt securities issued by NFCs, NSA mil. local currency | D57: Q | F57: Millions of Euros | G57: SDW | H57: QSA | I57: QSA.Q.N.PT.W0.S11.S1.N.L.LE.F3.T._Z.XDC._T.S.V.N._T
C58: C: Total trade credit granted to NFCs, NSA mil. local currency | D58: Q | F58: Millions of Euros | G58: SDW | H58: QSA | I58: QSA.Q.N.PT.W0.S11.S1.N.L.LE.F81.T._Z.XDC._T.S.V.N._T
C59: Total credit to NFC, longer time series | D59: Q | E59: used for backasting* | G59: SDW
C60: GDPN: Gross domestic product, nominal
C61: Gross domestic product, nominal | D61: Q | F61: Millions of Euros | G61: SDW | H61: MNA | I61: MNA.Q.Y.PT.W2.S1.S1.B.B1GQ._Z._Z._Z.XDC.V.N
C62: Gross domestic product, nominal - longer time series | D62: Q | E62: merged with main series for backasting (earlier dates using ECB values since no Haver access) | G62: Haver | H62: Haver | I62: A???GDP@OECDNAQ
B63: C7 - Loans to HHs for house purchases, 3-year av. growth | C63: LHP: Lending for house purchase (stock) | D63: Q | F63: Millions of Euros | G63: SDW | H63: BSI | I63: BSI.M.PT.N.A.A22.A.1.U2.2250.Z01.E
C64: CPI
C65: HICP, SA 2015 = 100 | D65: M | E65: average over period | F65: index 2015 = 100 | G65: SDW | H65: ICP | I65: ICP.M.PT.Y.000000.3.INX | J65: 17 working days after the end of the reference month
C66: HICP SA long series, 2010 = 100 | D66: Q | E66: used for backasting* | F66: index 2015 = 100 - rebased | G66: SDW-OECD | H66: MEI | I66: MEI.Q.PT.CPALTT01.IXOB
B67: C8 - HH debt, % of income | C67: HH debt, % of income | D67: Q | F67: Percentage points | G67: SDW | H67: QSA | I67: QSA.Q.N.PT.W0.S1M.S1.N.L.LE.F4.T._Z.XDC_R_B6G_CY._T.S.V.N._T
B68: C9 - RRE price-to-income ratio, 3-year av. Growth | C68: RRE_HPI_B: Deviation of the house price to income ratio from its average since 1996Q1 | D68: Q | F68: Percentage points | G68: SDW | H68: RESV | I68: RESV.Q.PT._T.N._TR.RVPI.4F0._Z._Z.RO | J68: two quarters before the current quarter for the quarterly series
B69: C10 - Real house price growth, 3-year av. growth | C69: RREPN: Transaction value - Index; Residential property, All dwelling types, new and existing | D69: Q | F69: index 2015 =100 | G69: SDW | H69: RESR | I69: RESR.Q.PT._T.N._TR.TVAL.4D0.TB.N.IX
C70: CPI
C71: HICP, SA 2015 = 100 | D71: M | E71: average over period | F71: index 2015 = 100 | G71: SDW | H71: ICP | I71: ICP.M.PT.Y.000000.3.INX | J71: 17 working days after the end of the reference month
C72: HICP SA long series, 2010 = 100 | D72: Q | E72: used for backasting* | F72: index 2015 = 100 - rebased | G72: SDW-OECD | H72: MEI | I72: MEI.Q.PT.CPALTT01.IXOB
B73: C11 - Debt service ratio, 2-year av. Change | C73: DSR: Debt service ratio =i*J/(1-(1+i)^-s)*Y | E73: currently not in use (but data from ECB, which is said to be base on this methodology used for backasting)
C74: J: Total credit to the non-financial private sector, seasonally adjusted | D74: Q | F74: Thousands of Euros | G74: SDW | H74: QSA | I74: (QSA.Q.N.PT.W0.S11.S1.N.L.LE.F4.T._Z.XDC._T.S.V.N._T + QSA.Q.N.PT.W0.S11.S1.N.L.LE.F3.T._Z.XDC._T.S.V.N._T+QSA.Q.N.PT.W0.S1M.S1.N.L.LE.F4.T._Z.XDC._T.S.V.N._T ) / 1000
C75: i: Weighted average interest rate (per annum) on the stock = [M*(O/O+P)+N*(P/O+P)]*(K/K+L) + I*(L/K+L)
C76: K: Credit to households | D76: Q | F76: Thousands of Euros | G76: SDW | H76: QSA | I76: (QSA.Q.N.PT.W0.S1M.S1.N.L.LE.F4.T._Z.XDC._T.S.V.N._T+QSA.Q.N.PT.W0.S1M.S1.N.L.LE.F3.T._Z.XDC._T.S.V.N._T)/1000
C77: L: Credit to NFC | D77: Q | F77: Thousands of Euros | G77: SDW | H77: QSA | I77: (QSA.Q.N.PT.W0.S11.S1.N.L.LE.F4.T._Z.XDC._T.S.V.N._T + QSA.Q.N.PT.W0.S11.S1.N.L.LE.F3.T._Z.XDC._T.S.V.N._T) / 1000
C78: I: Bank interest rates - loans to corporations (outstanding amounts) | D78: M | E78: end of quarter values | F78: Percent per annum | G78: SDW | H78: MIR | I78: MIR.M.PT.B.A20.A.R.A.2240.EUR.O
C79: M: Bank interest rates - loans to households for house purchase (outstanding amounts) | D79: M | E79: end of quarter values | F79: Percent per annum | G79: SDW | H79: MIR | I79: MIR.M.PT.B.A22.A.R.A.2250.EUR.O
C80: N: Bank interest rates - loans to households for consumption APRC (new business) | D80: M | E80: end of quarter values | F80: Percent per annum | G80: SDW | H80: MIR | I80: MIR.M.PT.B.A2B.A.C.A.2250.EUR.N
C81: O: Lending for house purchase vis-a-vis euro area households reported by MFI excluding ESCB in Portugal (stock) | D81: M | E81: end of quarter values | F81: Millions of Euros | G81: SDW | H81: BSI | I81: BSI.M.PT.N.A.A22.A.1.U2.2250.Z01.E
C82: P: Credit for consumption vis-a-vis euro area households reported by MFI excluding ESCB in Portugal (stock) | D82: M | E82: end of quarter values | F82: Millions of Euros | G82: SDW | H82: BSI | I82: BSI.M.PT.N.A.A21.A.1.U2.2250.Z01.E
C83: s: Weighted average maturity (by loan volumes) = 0.5*(B/A+E)+3*(C/A+E)+15*(D/A+E) + 0.5*(F/A+E)+3*(G/A+E)+15*(H/A+E) | E83: Assumption: an average maturity within original maturity tranches (up to one year, between one and five, above five years) of 0.5, 3 and 15 years respectively
C84: A: Loans vis-a-vis domestic households reported by MFI excluding ESCB in Portugal (stock), total maturity | D84: M | E84: end of quarter values | F84: Millions of Euros | G84: SDW | H84: BSI | I84: BSI.M.PT.N.A.A20.A.1.U6.2250.Z01.E
C85: B: Outstanding amounts at the end of the period (stocks), MFIs excluding ESCB reporting sector - Loans, Up to 1 year maturity, HH | D85: M | E85: end of quarter values | F85: Millions of Euros | G85: SDW | H85: BSI | I85: BSI.M.PT.N.A.A20.F.1.U6.2250.Z01.E
C86: C: Outstanding amounts at the end of the period (stocks), MFIs excluding ESCB reporting sector - Loans, Over 1 and up to 5 years maturity, HH | D86: M | E86: end of quarter values | F86: Millions of Euros | G86: SDW | H86: BSI | I86: BSI.M.PT.N.A.A20.I.1.U6.2250.Z01.E
C87: D: Outstanding amounts at the end of the period (stocks), MFIs excluding ESCB reporting sector - Loans, Over 5 years maturity, HH | D87: M | E87: end of quarter values | F87: Millions of Euros | G87: SDW | H87: BSI | I87: BSI.M.PT.N.A.A20.J.1.U6.2250.Z01.E
C88: E: Loans vis-a-vis domestic NFC reported by MFI excluding ESCB in Portugal (stock), all maturities | D88: M | E88: end of quarter values | F88: Millions of Euros | G88: SDW | H88: BSI | I88: BSI.M.PT.N.A.A20.A.1.U6.2240.Z01.E
C89: F: Outstanding amounts at the end of the period (stocks), MFIs excluding ESCB reporting sector - Loans, Up to 1 year maturity, NFC | D89: M | E89: end of quarter values | F89: Millions of Euros | G89: SDW | H89: BSI | I89: BSI.M.PT.N.A.A20.F.1.U6.2240.Z01.E
C90: G: Outstanding amounts at the end of the period (stocks), MFIs excluding ESCB reporting sector - Loans, Over 1 and up to 5 years maturity, NFC | D90: M | E90: end of quarter values | F90: Millions of Euros | G90: SDW | H90: BSI | I90: BSI.M.PT.N.A.A20.I.1.U6.2240.Z01.E
C91: H: Outstanding amounts at the end of the period (stocks), MFIs excluding ESCB reporting sector - Loans, Over 5 years maturity, NFC | D91: M | E91: end of quarter values | F91: Millions of Euros | G91: SDW | H91: BSI | I91: BSI.M.PT.N.A.A20.J.1.U6.2240.Z01.E
C92: Y - aggregate income (annualized) | D92: Q | F92: Millions of Euros | G92: SDW | H92: MNA | I92: MNA.Q.N.PT.W2.S1.S1.B.B1GQ._Z._Z._Z.XDC.V.N
C93: DSR: Debt service ratio as calculated by BIS | D93: Q | F93: Percentage points | G93: BIS | I93: https://www.bis.org/statistics/dsr.htm?m=6%7C380%7C671
C94: Notes: * In order to backcast the (quarterly) series to_be_completed (e.g. available only from 2010Q1) on the basis of series reference (available from e.g. 1977Q1) first the (quarterly) “shrinkage rate” of the reference series is calculated as follows: shrinkage (t) = ( reference (t-1) – reference (t) ) / reference (t).The shrinkage rate is then used on the to_be_completed series as follows: to_be_completed (2009Q4) = to_be_completed (2010Q1) ( 1 + shrinkage (2010Q1) ). The calculation is in fact applied recursively for all periods prior to 2010Q1 as follows to_be_completed (t-1) = to_be_completed (t) ( 1 + shrinkage (t) ).

Sheet Metadata_adapted
C1: MPR Cyclical Scoreboard
B2: Code | C2: Indicator (untransformed) | D2: Data provider | E2: Dataset
A3: C2 | B3: CTN3R | C3: Total credit (unconsolidated - including trade credit), deflated by CPIP | D3: SDW | E3: QSA, BISM, IEAQ, ICP, MEI
A4: C1 | B4: CBNFA_GDP | C4: Bank credit to NFPS (adjusted by securitisation) to GDP | D4: SDW | E4: BSI, BISM, MNA, ESA
A5: C9 | B5: RRE_HPI_B | C5: Nominal House price-to-income | D5: ECB - DG-E / OECD /SDW | E5: RPV
A6: C3 | B6: CA2GDPEUR | C6: Current account balance to GDP | D6: SDW | E6: BP6, ST1, OEO, MNA, ESA
A7: C11 | B7: DSR | C7: Debt service ratio | D7: SDW/ BIS | E7: QSA, MIR, BSI, MNA
A8: C4 | B8: NLS | C8: Spreads new lending private non-financial sector | D8: SDW | E8: RAI
B10: Methodology: | C10: 2018-05-23 Item 2 MPR technical appendix | D10: MPR
C11: CRAR | D11: CRAR
B13: Code | C13: Underlying indicators | D13: Original frequency | E13: Aggregation method/ observations | F13: Unit | G13: Data provider | H13: Dataset | I13: SDW code | J13: Available in dd-mm-yy (quarter available)
B14: C1 - Bank credit-to-GDP ratio, 2-year av. change | C14: CBNFA: Bank credit to NFPS - adjusted by securitisation (=A+B+C+D)
C15: A: Loans to NFCs - adjusted by securitization | D15: M | E15: end of quarter values | F15: Millions of Euros | G15: SDW | H15: BSI | I15: BSI.M.PT.N.A.A20T.A.1.U6.2240.Z01.E
C16: B: Loans to HHs - adjusted by securitization | D16: M | E16: end of quarter values | F16: Millions of Euros | G16: SDW | H16: BSI | I16: BSI.M.PT.N.A.A20T.A.1.U6.2250.Z01.E
C17: C: Debt securities of NFC | D17: Q | F17: Millions of Euros | G17: SDW | H17: BSI | I17: BSI.Q.PT.N.A.A30.A.1.U6.2240.Z01.E
C18: D: Debt securities of HHs | D18: Q | F18: Millions of Euros | G18: SDW | H18: BSI | I18: BSI.Q.PT.N.A.A30.A.1.U6.2250.Z01.E
C19: Loans + debt securities to nonfin private sector - longer time series | D19: Q | E19: used for backasting* | G19: BIS | I19: https://www.bis.org/statistics/totcredit.htm
C20: GDPN: Gross domestic product, nominal
C21: Gross domestic product, nominal | D21: Q | F21: Millions of Euros | G21: SDW | H21: MNA | I21: MNA.Q.Y.PT.W2.S1.S1.B.B1GQ._Z._Z._Z.XDC.V.N
C22: Gross domestic product, nominal - longer time series | D22: Q | E22: merged with main series for backasting (earlier dates using ECB values since no Haver access) | G22: Haver | H22: Haver | I22: A???GDP@OECDNAQ
B23: C2 - Real total credit, 2-year av. growth | C23: CTHHN: Total credit to HHs (=A+B)
C24: A: QSA loans to HHs, NSA mil. local currency | D24: Q | F24: Millions of Euros | G24: SDW | H24: QSA | I24: QSA.Q.N.PT.W0.S1M.S1.N.L.LE.F4.T._Z.XDC._T.S.V.N._T
C25: B: QSA debt sec issued by HHs, NSA mil. local currency | D25: Q | F25: Millions of Euros | G25: SDW | H25: QSA | I25: QSA.Q.N.PT.W0.S1M.S1.N.L.LE.F3.T._Z.XDC._T.S.V.N._T
C26: Total credit to HHs, longer time series | D26: Q | E26: used for backasting* | G26: SDW | H26: QSA
C27: CTNFCN3: Total credit to NFCs - unconsolidated (including trade credit) (=A+B+C)
C28: A: Total loans to NFCs, NSA mil. local currency | D28: Q | F28: Millions of Euros | G28: SDW | H28: QSA | I28: QSA.Q.N.PT.W0.S11.S1.N.L.LE.F4.T._Z.XDC._T.S.V.N._T
C29: B: Total debt securities issued by NFCs, NSA mil. local currency | D29: Q | F29: Millions of Euros | G29: SDW | H29: QSA | I29: QSA.Q.N.PT.W0.S11.S1.N.L.LE.F3.T._Z.XDC._T.S.V.N._T
C30: C: Total trade credit granted to NFCs, NSA mil. local currency | D30: Q | F30: Millions of Euros | G30: SDW | H30: QSA | I30: QSA.Q.N.PT.W0.S11.S1.N.L.LE.F81.T._Z.XDC._T.S.V.N._T
C31: Total credit to NFC, longer time series | D31: Q | E31: used for backasting* | G31: SDW
C32: CPI
C33: HICP, SA 2015 = 100 | D33: M | E33: average over period | F33: index 2015 = 100 | G33: SDW | H33: ICP | I33: ICP.M.PT.Y.000000.3.INX | J33: 17 working days after the end of the reference month
C34: HICP SA long series, 2010 = 100 | D34: Q | E34: used for backasting* | F34: index 2015 = 100 - rebased | G34: SDW-OECD | H34: MEI | I34: MEI.Q.PT.CPALTT01.IXOB
B35: C3 - Current account balance, % of GDP | C35: CA2GDPEUR: Current account balance to GDP (4Q mov SUM A / 4Q mov SUM B)
C36: Current account (A) | D36: Q | F36: Millions of Euros | G36: SDW | H36: BP6 | I36: BP6.Q.N.PT.W1.S1.S1.T.B.CA._Z._Z._Z.EUR._T._X.N
C37: Current account, long time series | D37: A | E37: used for backasting* / interpolation with annual values | F37: Euros | G37: SDW-OECD | H37: OEO (ecoconomic outlook of OECD) | I37: OEO.Q.PRT.CB
C38: GDPN: Nominal Gross Domestic Product
C39: Nominal Gross Domestic Product (B) | D39: Q | F39: Millions of Euros | G39: SDW | H39: MNA | I39: MNA.Q.N.PT.W2.S1.S1.B.B1GQ._Z._Z._Z.EUR.V.N
D40: A | E40: used for backasting* / interpolation with annual values | F40: Euros | G40: SDW-OECD | H40: OEO (ecoconomic outlook of OECD) | I40: OEO.Q.PT.GDP
B41: C4 - NFPS lending spreads, 2-year av. change | C41: NLS: Spreads new lending private non-financial sector | D41: M | E41: end of quarter values | F41: Percentage points | G41: SDW | H41: RAI | I41: RAI.M.PT.LMGBLNFCH.EUR.MIR.Z
B42: C5 - Bank credit-to-GDP gap | C42: CBNFA: Bank credit to NFPS - adjusted by securitisation (=A+B+C+D)
C43: A: Loans to NFCs - adjusted by securitization | D43: M | E43: end of quarter values | F43: Millions of Euros | G43: SDW | H43: BSI | I43: BSI.M.PT.N.A.A20T.A.1.U6.2240.Z01.E
C44: B: Loans to HHs - adjusted by securitization | D44: M | E44: end of quarter values | F44: Millions of Euros | G44: SDW | H44: BSI | I44: BSI.M.PT.N.A.A20T.A.1.U6.2250.Z01.E
C45: C: Debt securities of NFC | D45: Q | F45: Millions of Euros | G45: SDW | H45: BSI | I45: BSI.Q.PT.N.A.A30.A.1.U6.2240.Z01.E
C46: D: Debt securities of HHs | D46: Q | F46: Millions of Euros | G46: SDW | H46: BSI | I46: BSI.Q.PT.N.A.A30.A.1.U6.2250.Z01.E
C47: Loans + debt securities to nonfin private sector - longer time series | D47: Q | E47: used for backasting* | G47: BIS | I47: https://www.bis.org/statistics/totcredit.htm
C48: GDPN: Gross domestic product, nominal
C49: Gross domestic product, nominal | D49: Q | F49: Millions of Euros | G49: SDW | H49: MNA | I49: MNA.Q.Y.PT.W2.S1.S1.B.B1GQ._Z._Z._Z.XDC.V.N
C50: Gross domestic product, nominal - longer time series | D50: Q | E50: merged with main series for backasting (earlier dates using ECB values since no Haver access) | G50: Haver | H50: Haver | I50: A???GDP@OECDNAQ
B51: C6 - Total credit-to-GDP gap | C51: CTHHN: Total credit to HHs (=A+B)
C52: A: QSA loans to HHs, NSA mil. local currency | D52: Q | F52: Millions of Euros | G52: SDW | H52: QSA | I52: QSA.Q.N.PT.W0.S1M.S1.N.L.LE.F4.T._Z.XDC._T.S.V.N._T
C53: B: QSA debt sec issued by HHs, NSA mil. local currency | D53: Q | F53: Millions of Euros | G53: SDW | H53: QSA | I53: QSA.Q.N.PT.W0.S1M.S1.N.L.LE.F3.T._Z.XDC._T.S.V.N._T
C54: Total credit to HHs, longer time series | D54: Q | E54: used for backasting* | G54: SDW | H54: QSA
C55: CTNFCN3: Total credit to NFCs - unconsolidated (including trade credit) (=A+B+C)
C56: A: Total loans to NFCs, NSA mil. local currency | D56: Q | F56: Millions of Euros | G56: SDW | H56: QSA | I56: QSA.Q.N.PT.W0.S11.S1.N.L.LE.F4.T._Z.XDC._T.S.V.N._T
C57: B: Total debt securities issued by NFCs, NSA mil. local currency | D57: Q | F57: Millions of Euros | G57: SDW | H57: QSA | I57: QSA.Q.N.PT.W0.S11.S1.N.L.LE.F3.T._Z.XDC._T.S.V.N._T
C58: C: Total trade credit granted to NFCs, NSA mil. local currency | D58: Q | F58: Millions of Euros | G58: SDW | H58: QSA | I58: QSA.Q.N.PT.W0.S11.S1.N.L.LE.F81.T._Z.XDC._T.S.V.N._T
C59: Total credit to NFC, longer time series | D59: Q | E59: used for backasting* | G59: SDW
C60: GDPN: Gross domestic product, nominal
C61: Gross domestic product, nominal | D61: Q | F61: Millions of Euros | G61: SDW | H61: MNA | I61: MNA.Q.Y.PT.W2.S1.S1.B.B1GQ._Z._Z._Z.XDC.V.N
C62: Gross domestic product, nominal - longer time series | D62: Q | E62: merged with main series for backasting (earlier dates using ECB values since no Haver access) | G62: Haver | H62: Haver | I62: A???GDP@OECDNAQ
B63: C7 - Loans to HHs for house purchases, 3-year av. growth | C63: LHP: Lending for house purchase (stock) | D63: Q | F63: Millions of Euros | G63: SDW | H63: BSI | I63: BSI.M.PT.N.A.A22.A.1.U2.2250.Z01.E
C64: CPI
C65: HICP, SA 2015 = 100 | D65: M | E65: average over period | F65: index 2015 = 100 | G65: SDW | H65: ICP | I65: ICP.M.PT.Y.000000.3.INX | J65: 17 working days after the end of the reference month
C66: HICP SA long series, 2010 = 100 | D66: Q | E66: used for backasting* | F66: index 2015 = 100 - rebased | G66: SDW-OECD | H66: MEI | I66: MEI.Q.PT.CPALTT01.IXOB
B67: C8 - HH debt, % of income | C67: HH debt, % of income | D67: Q | F67: Percentage points | G67: SDW | H67: QSA | I67: QSA.Q.N.PT.W0.S1M.S1.N.L.LE.F4.T._Z.XDC_R_B6G_CY._T.S.V.N._T
B68: C9 - RRE price-to-income ratio, 3-year av. Growth | C68: RRE_HPI_B: Deviation of the house price to income ratio from its average since 1996Q1 | D68: Q | F68: Percentage points | G68: SDW | H68: RESV | I68: RESV.Q.PT._T.N._TR.RVPI.4F0._Z._Z.RO | J68: two quarters before the current quarter for the quarterly series
B69: C10 - Real house price growth, 3-year av. growth | C69: RREPN: Transaction value - Index; Residential property, All dwelling types, new and existing | D69: Q | F69: index 2015 =100 | G69: SDW | H69: RESR | I69: RESR.Q.PT._T.N._TR.TVAL.4D0.TB.N.IX
C70: CPI
C71: HICP, SA 2015 = 100 | D71: M | E71: average over period | F71: index 2015 = 100 | G71: SDW | H71: ICP | I71: ICP.M.PT.Y.000000.3.INX | J71: 17 working days after the end of the reference month
C72: HICP SA long series, 2010 = 100 | D72: Q | E72: used for backasting* | F72: index 2015 = 100 - rebased | G72: SDW-OECD | H72: MEI | I72: MEI.Q.PT.CPALTT01.IXOB
B73: C11 - Debt service ratio, 2-year av. Change | C73: DSR: Debt service ratio =i*J/(1-(1+i)^-s)*Y | E73: currently not in use (but data from ECB, which is said to be base on this methodology used for backasting)
C74: J: Total credit to the non-financial private sector, seasonally adjusted | D74: Q | F74: Thousands of Euros | G74: SDW | H74: QSA | I74: (QSA.Q.N.PT.W0.S11.S1.N.L.LE.F4.T._Z.XDC._T.S.V.N._T + QSA.Q.N.PT.W0.S11.S1.N.L.LE.F3.T._Z.XDC._T.S.V.N._T+QSA.Q.N.PT.W0.S1M.S1.N.L.LE.F4.T._Z.XDC._T.S.V.N._T ) / 1000
C75: i: Weighted average interest rate (per annum) on the stock = [M*(O/O+P)+N*(P/O+P)]*(K/K+L) + I*(L/K+L)
C76: K: Credit to households | D76: Q | F76: Thousands of Euros | G76: SDW | H76: QSA | I76: (QSA.Q.N.PT.W0.S1M.S1.N.L.LE.F4.T._Z.XDC._T.S.V.N._T+QSA.Q.N.PT.W0.S1M.S1.N.L.LE.F3.T._Z.XDC._T.S.V.N._T)/1000
C77: L: Credit to NFC | D77: Q | F77: Thousands of Euros | G77: SDW | H77: QSA | I77: (QSA.Q.N.PT.W0.S11.S1.N.L.LE.F4.T._Z.XDC._T.S.V.N._T + QSA.Q.N.PT.W0.S11.S1.N.L.LE.F3.T._Z.XDC._T.S.V.N._T) / 1000
C78: I: Bank interest rates - loans to corporations (outstanding amounts) | D78: M | E78: end of quarter values | F78: Percent per annum | G78: SDW | H78: MIR | I78: MIR.M.PT.B.A20.A.R.A.2240.EUR.O
C79: M: Bank interest rates - loans to households for house purchase (outstanding amounts) | D79: M | E79: end of quarter values | F79: Percent per annum | G79: SDW | H79: MIR | I79: MIR.M.PT.B.A22.A.R.A.2250.EUR.O
C80: N: Bank interest rates - loans to households for consumption APRC (new business) | D80: M | E80: end of quarter values | F80: Percent per annum | G80: SDW | H80: MIR | I80: MIR.M.PT.B.A2B.A.C.A.2250.EUR.N
C81: O: Lending for house purchase vis-a-vis euro area households reported by MFI excluding ESCB in Portugal (stock) | D81: M | E81: end of quarter values | F81: Millions of Euros | G81: SDW | H81: BSI | I81: BSI.M.PT.N.A.A22.A.1.U2.2250.Z01.E
C82: P: Credit for consumption vis-a-vis euro area households reported by MFI excluding ESCB in Portugal (stock) | D82: M | E82: end of quarter values | F82: Millions of Euros | G82: SDW | H82: BSI | I82: BSI.M.PT.N.A.A21.A.1.U2.2250.Z01.E
C83: s: Weighted average maturity (by loan volumes) = 0.5*(B/A+E)+3*(C/A+E)+15*(D/A+E) + 0.5*(F/A+E)+3*(G/A+E)+15*(H/A+E) | E83: Assumption: an average maturity within original maturity tranches (up to one year, between one and five, above five years) of 0.5, 3 and 15 years respectively
C84: A: Loans vis-a-vis domestic households reported by MFI excluding ESCB in Portugal (stock), total maturity | D84: M | E84: end of quarter values | F84: Millions of Euros | G84: SDW | H84: BSI | I84: BSI.M.PT.N.A.A20.A.1.U6.2250.Z01.E
C85: B: Outstanding amounts at the end of the period (stocks), MFIs excluding ESCB reporting sector - Loans, Up to 1 year maturity, HH | D85: M | E85: end of quarter values | F85: Millions of Euros | G85: SDW | H85: BSI | I85: BSI.M.PT.N.A.A20.F.1.U6.2250.Z01.E
C86: C: Outstanding amounts at the end of the period (stocks), MFIs excluding ESCB reporting sector - Loans, Over 1 and up to 5 years maturity, HH | D86: M | E86: end of quarter values | F86: Millions of Euros | G86: SDW | H86: BSI | I86: BSI.M.PT.N.A.A20.I.1.U6.2250.Z01.E
C87: D: Outstanding amounts at the end of the period (stocks), MFIs excluding ESCB reporting sector - Loans, Over 5 years maturity, HH | D87: M | E87: end of quarter values | F87: Millions of Euros | G87: SDW | H87: BSI | I87: BSI.M.PT.N.A.A20.J.1.U6.2250.Z01.E
C88: E: Loans vis-a-vis domestic NFC reported by MFI excluding ESCB in Portugal (stock), all maturities | D88: M | E88: end of quarter values | F88: Millions of Euros | G88: SDW | H88: BSI | I88: BSI.M.PT.N.A.A20.A.1.U6.2240.Z01.E
C89: F: Outstanding amounts at the end of the period (stocks), MFIs excluding ESCB reporting sector - Loans, Up to 1 year maturity, NFC | D89: M | E89: end of quarter values | F89: Millions of Euros | G89: SDW | H89: BSI | I89: BSI.M.PT.N.A.A20.F.1.U6.2240.Z01.E
C90: G: Outstanding amounts at the end of the period (stocks), MFIs excluding ESCB reporting sector - Loans, Over 1 and up to 5 years maturity, NFC | D90: M | E90: end of quarter values | F90: Millions of Euros | G90: SDW | H90: BSI | I90: BSI.M.PT.N.A.A20.I.1.U6.2240.Z01.E
C91: H: Outstanding amounts at the end of the period (stocks), MFIs excluding ESCB reporting sector - Loans, Over 5 years maturity, NFC | D91: M | E91: end of quarter values | F91: Millions of Euros | G91: SDW | H91: BSI | I91: BSI.M.PT.N.A.A20.J.1.U6.2240.Z01.E
C92: Y - aggregate income (annualized) | D92: Q | F92: Millions of Euros | G92: SDW | H92: MNA | I92: MNA.Q.N.PT.W2.S1.S1.B.B1GQ._Z._Z._Z.XDC.V.N
C93: DSR: Debt service ratio as calculated by BIS | D93: Q | F93: Percentage points | G93: BIS | I93: https://www.bis.org/statistics/dsr.htm?m=6%7C380%7C671
C94: Notes: * In order to backcast the (quarterly) series to_be_completed (e.g. available only from 2010Q1) on the basis of series reference (available from e.g. 1977Q1) first the (quarterly) “shrinkage rate” of the reference series is calculated as follows: shrinkage (t) = ( reference (t-1) – reference (t) ) / reference (t).The shrinkage rate is then used on the to_be_completed series as follows: to_be_completed (2009Q4) = to_be_completed (2010Q1) ( 1 + shrinkage (2010Q1) ). The calculation is in fact applied recursively for all periods prior to 2010Q1 as follows to_be_completed (t-1) = to_be_completed (t) ( 1 + shrinkage (t) ).
