Workbook

Sheet C
AU1: 1
AB30: 1

Sheet ToC
D2: Table of content
AB3: Scoreboard for residential real estate risks
AB4: ="August 2022" -> August 2022
B5: 1 | D5: Scoreboard for residential real estate (RRE) risks
B7: 2 | D7: Charts for Portuguese indicators (RRE scoreboard)
B9: 3 | D9: Scoreboard for potential for spillovers (exposure to RRE)
B11: 4 | D11: Charts for Portuguese indicators (potential for spillovers scoreboard)
B13: 5 | D13: Appendix
AA23: 1

Sheet 1.RRE SB
B2: =+ToC!B5 -> 1 | C2: =+ToC!D5 -> Scoreboard for residential real estate (RRE) risks
T3: =+ToC!AB3 -> Scoreboard for residential real estate risks
T4: =+ToC!AB4 -> August 2022 | AC4: Price Growth | AF4: RRE Trend | AI4: Price to Income | AL4: Econometric Model
C5: =+"1.1. Table with latest published data - "&"available at"&" "&T4 -> 1.1. Table with latest published data - available at August 2022 | J5: (see appendix to check the reference date by country and indicator) | AC5: Threshold | AD5: Risk | AF5: Threshold | AG5: Risk | AI5: Threshold | AJ5: Risk | AL5: Threshold | AM5: Risk
AC6: =+'[1]1 Price Growth'!$X$3 -> 2.5 | AD6: TR1 | AF6: =+'[1]2RRE trend'!X3 -> 1 | AG6: TR1 | AI6: =+'[1]3_Price to Income'!X3 -> 4 | AJ6: TR1 | AL6: =+'[1]4_EconometricModel'!X3 -> 0 | AM6: TR1
D7: =[1]Scoreboards!D32 -> Indicators | N7: =[1]Scoreboards!N31 -> SUMMARY MEASURES | O7: =[2]Scoreboards!O31 -> 0 | P7: =[1]Scoreboards!P31 -> ALTERNATIVE SUMMARY MEASURES | Q7: =[2]Scoreboards!Q31 -> 0 | R7: =[2]Scoreboards!R31 -> 0 | AC7: =+'[1]1 Price Growth'!$X$4 -> 5 | AD7: TR2 | AF7: =+'[1]2RRE trend'!X4 -> 1.04 | AG7: TR2 | AI7: =+'[1]3_Price to Income'!X4 -> 10 | AJ7: TR2 | AL7: =+'[1]4_EconometricModel'!X4 -> 6 | AM7: TR2
N8: =[2]Scoreboards!N32 -> 0 | O8: =[2]Scoreboards!O32 -> 0 | P8: =[2]Scoreboards!P32 -> 0 | Q8: =[2]Scoreboards!Q32 -> 0 | R8: =[2]Scoreboards!R32 -> 0 | AC8: =+'[1]1 Price Growth'!$X$5 -> 7.5 | AD8: TR3 | AF8: =+'[1]2RRE trend'!X5 -> 1.08 | AG8: TR3 | AI8: =+'[1]3_Price to Income'!X5 -> 16 | AJ8: TR3 | AL8: =+'[1]4_EconometricModel'!X5 -> 12 | AM8: TR3
D9: =[1]Scoreboards!D33 -> Price indicators | E9: =[2]Scoreboards!E33 -> 0 | F9: =[2]Scoreboards!F33 -> 0 | G9: =[2]Scoreboards!G33 -> 0 | H9: =[1]Scoreboards!H33 -> Lending indicators | I9: =[2]Scoreboards!I33 -> 0 | J9: =[2]Scoreboards!J33 -> 0 | K9: =[1]Scoreboards!K33 -> Household balance sheet | L9: =[2]Scoreboards!L33 -> 0 | M9: =[2]Scoreboards!M33 -> 0
C10: =[1]Scoreboards!C34 -> Country | D10: =[1]Scoreboards!D34 -> Residential real estate price index, 36m real growth, % | E10: =[1]Scoreboards!E34 -> Residential price index relative to trend | F10: =[1]Scoreboards!F34 -> House price to income ratio (deviation from historical average in %) | G10: =[1]Scoreboards!G34 -> Econometric Model | H10: =[1]Scoreboards!H34 -> Loans to HH for house purchase, 36m real growth, % | I10: =[1]Scoreboards!I34 -> Loans to HH for HP relative to trend | J10: =[1]Scoreboards!J34 -> HH Loan Spread | ... R10: =[1]Scoreboards!R34 -> Household Balance Sheet Composite Indicator | AC10: Loans to HH for HP Growth | AF10: Loans to HH for HP trend | AI10: Spreads | AL10: HH Debt to income | AO10: Average Rating
C11: =[1]Scoreboards!C35 -> Austria | D11: =[1]Scoreboards!D35 -> 6.3297412 | E11: =[1]Scoreboards!E35 -> 1.1140437 | F11: =[1]Scoreboards!F35 -> 54 | G11: =[1]Scoreboards!G35 -> 24 | H11: =[1]Scoreboards!H35 -> 3.6721088 | I11: =[1]Scoreboards!I35 -> 0.99007554 | J11: =[1]Scoreboards!J35 -> 1.5828 | ... R11: =[1]Scoreboards!R35 -> 0.11479758 | AC11: Threshold | AD11: Risk | AF11: Threshold | AG11: Risk | AI11: Threshold | AJ11: Risk | AL11: Threshold | AM11: Risk | AO11: Percentiles | AP11: Threshold | AQ11: Risk
C12: =[1]Scoreboards!C36 -> Belgium | D12: =[1]Scoreboards!D36 -> 3.339496 | E12: =[1]Scoreboards!E36 -> 0.99251737 | F12: =[1]Scoreboards!F36 -> 22.527795 | G12: =[1]Scoreboards!G36 -> -3 | H12: =[1]Scoreboards!H36 -> 5.7312329 | I12: =[1]Scoreboards!I36 -> 1.0950947 | J12: =[1]Scoreboards!J36 -> 1.9242 | ... R12: =[1]Scoreboards!R36 -> 0.010063866 | AC12: =+'[1]5 Loans to HH for HP Growth'!X3 -> 3 | AD12: TR1 | AF12: =+'[1]6Loans to HH for HP trend'!X3 -> 1.05 | AG12: TR1 | AI12: =+'[1]7_Spreads'!X3 -> 2 | AJ12: TR1 | AL12: =+'[1]8_HH Debt to income'!X3 -> 75 | AM12: TR1 | AO12: =+'[1]Average Rating'!W3 -> - | AP12: =+'[1]Average Rating'!X3 -> 1 | AQ12: TR1
C13: =[1]Scoreboards!C37 -> Cyprus | D13: =[1]Scoreboards!D37 -> 0.054731858 | E13: =[1]Scoreboards!E37 -> 1.1723241 | F13: =[1]Scoreboards!F37 -> -8 | G13: =[1]Scoreboards!G37 -> -18 | H13: =[1]Scoreboards!H37 -> 0.22377576 | I13: =[1]Scoreboards!I37 -> 0.77260109 | J13: =[1]Scoreboards!J37 -> 2.2118 | ... R13: =[1]Scoreboards!R37 -> 0.58341549 | AC13: =+'[1]5 Loans to HH for HP Growth'!X4 -> 6 | AD13: TR2 | AF13: =+'[1]6Loans to HH for HP trend'!X4 -> 1.1 | AG13: TR2 | AI13: =+'[1]7_Spreads'!X4 -> 1.5 | AJ13: TR2 | AL13: =+'[1]8_HH Debt to income'!X4 -> 85 | AM13: TR2 | AO13: =+'[1]Average Rating'!W4 -> 0.8 | AP13: =+'[1]Average Rating'!X4 -> 1.4 | AQ13: TR2
C14: =[1]Scoreboards!C38 -> Germany | D14: =[1]Scoreboards!D38 -> 6.2677516 | E14: =[1]Scoreboards!E38 -> 1.1236509 | F14: =[1]Scoreboards!F38 -> 31 | G14: =[1]Scoreboards!G38 -> 21 | H14: =[1]Scoreboards!H38 -> 2.9321418 | I14: =[1]Scoreboards!I38 -> 1.0673371 | J14: =[1]Scoreboards!J38 -> 2.5866 | ... R14: =[1]Scoreboards!R38 -> 0.06342097 | AC14: =+'[1]5 Loans to HH for HP Growth'!X5 -> 9 | AD14: TR3 | AF14: =+'[1]6Loans to HH for HP trend'!X5 -> 1.15 | AG14: TR3 | AI14: =+'[1]7_Spreads'!X5 -> 1 | AJ14: TR3 | AL14: =+'[1]8_HH Debt to income'!X5 -> 95 | AM14: TR3 | AO14: =+'[1]Average Rating'!W5 -> 0.9 | AP14: =+'[1]Average Rating'!X5 -> 1.7 | AQ14: TR3
C15: =[1]Scoreboards!C39 -> Estonia | D15: =[1]Scoreboards!D39 -> 7.8173835 | E15: =[1]Scoreboards!E39 -> 1.1579816 | F15: =[1]Scoreboards!F39 -> 19 | G15: =[1]Scoreboards!G39 -> -2 | H15: =[1]Scoreboards!H39 -> 1.2196945 | I15: =[1]Scoreboards!I39 -> 1.01153 | J15: =[1]Scoreboards!J39 -> 1.4858 | ... R15: =[1]Scoreboards!R39 -> -0.16690984
C16: =[1]Scoreboards!C40 -> Spain | D16: =[1]Scoreboards!D40 -> 4.8737814 | E16: =[1]Scoreboards!E40 -> 1.0006018 | F16: =[1]Scoreboards!F40 -> 12 | G16: =[1]Scoreboards!G40 -> 3 | H16: =[1]Scoreboards!H40 -> -3.7060513 | I16: =[1]Scoreboards!I40 -> 0.85706441 | J16: =[1]Scoreboards!J40 -> 1.6015 | ... R16: =[1]Scoreboards!R40 -> -0.086264796
C17: =[1]Scoreboards!C41 -> Finland | D17: =[1]Scoreboards!D41 -> 0.80329508 | E17: =[1]Scoreboards!E41 -> 1.0001977 | F17: =[1]Scoreboards!F41 -> 7.2018276 | G17: =[1]Scoreboards!G41 -> 1 | H17: =[1]Scoreboards!H41 -> 0.20011284 | I17: =[1]Scoreboards!I41 -> 0.90758301 | J17: =[1]Scoreboards!J41 -> 0.88 | ... R17: =[1]Scoreboards!R41 -> 0.64822791 | AC17: Financial Assets to Debt
C18: =[1]Scoreboards!C42 -> France | D18: =[1]Scoreboards!D42 -> 4.204176 | E18: =[1]Scoreboards!E42 -> 1.0154149 | F18: =[1]Scoreboards!F42 -> 23.790759 | G18: =[1]Scoreboards!G42 -> -2 | H18: =[1]Scoreboards!H42 -> 4.0954765 | I18: =[1]Scoreboards!I42 -> 0.99975322 | J18: =[1]Scoreboards!J42 -> 1.2169 | ... R18: =[1]Scoreboards!R42 -> 0.27792789 | AF18: DSTI | AO18: Composite Indicator
C19: =[1]Scoreboards!C43 -> Greece | D19: =[1]Scoreboards!D43 -> 5.1431387 | E19: =[1]Scoreboards!E43 -> 1.1611631 | F19: =[1]Scoreboards!F43 -> 8.7661801 | G19: =[1]Scoreboards!G43 -> -9 | H19: =[1]Scoreboards!H43 -> -11.128574 | I19: =[1]Scoreboards!I43 -> 0.50081775 | J19: =[1]Scoreboards!J43 -> 2.8412 | ... R19: =[1]Scoreboards!R43 -> 0.15527847 | AC19: Threshold | AD19: Risk | AF19: Thresholds | AG19: Risk | AO19: Percentiles | AP19: Threshold | AQ19: Risk
C20: =[1]Scoreboards!C44 -> Ireland | D20: =[1]Scoreboards!D44 -> 9.5556579 | E20: =[1]Scoreboards!E44 -> 1.215847 | F20: =[1]Scoreboards!F44 -> 8 | G20: =[1]Scoreboards!G44 -> -11 | H20: =[1]Scoreboards!H44 -> -5.1130628 | I20: =[1]Scoreboards!I44 -> 1.0708002 | J20: =[1]Scoreboards!J44 -> 2.9591 | ... R20: =[1]Scoreboards!R44 -> 0.0060364516 | AC20: =+'[1]9financialassetstodebt'!X3 -> 280 | AD20: TR1 | AF20: =+'[1]10_DSTI'!X3 -> 10 | AG20: TR1 | AO20: =+'[1]Composite Indicator'!X3 -> - | AP20: =+'[1]Composite Indicator'!Y3 -> 0 | AQ20: TR1
C21: =[1]Scoreboards!C45 -> Italy | D21: =[1]Scoreboards!D45 -> -1.4212527 | E21: =[1]Scoreboards!E45 -> 0.88693488 | F21: =[1]Scoreboards!F45 -> -6 | G21: =[1]Scoreboards!G45 -> -15 | H21: =[1]Scoreboards!H45 -> 0.53693681 | I21: =[1]Scoreboards!I45 -> 0.91424171 | J21: =[1]Scoreboards!J45 -> 1.682 | ... R21: =[1]Scoreboards!R45 -> -0.37814327 | AC21: =+'[1]9financialassetstodebt'!X4 -> 260 | AD21: TR2 | AF21: =+'[1]10_DSTI'!X4 -> 12 | AG21: TR2 | AO21: =+'[1]Composite Indicator'!X4 -> 0.8 | AP21: =+'[1]Composite Indicator'!Y4 -> 0.26661354 | AQ21: TR2
C22: =[1]Scoreboards!C46 -> Lithuania | D22: =[1]Scoreboards!D46 -> 4.9783281 | E22: =[1]Scoreboards!E46 -> 1.0638983 | F22: =[1]Scoreboards!F46 -> 3 | G22: =[1]Scoreboards!G46 -> -5 | H22: =[1]Scoreboards!H46 -> 3.2164103 | I22: =[1]Scoreboards!I46 -> 0.95216803 | J22: =[1]Scoreboards!J46 -> 1.8685 | ... R22: =[1]Scoreboards!R46 -> -0.57454656 | AC22: =+'[1]9financialassetstodebt'!X5 -> 240 | AD22: TR3 | AF22: =+'[1]10_DSTI'!X5 -> 14 | AG22: TR3 | AO22: =+'[1]Composite Indicator'!X5 -> 0.9 | AP22: =+'[1]Composite Indicator'!Y5 -> 0.48269411 | AQ22: TR3
C23: =[1]Scoreboards!C47 -> Luxembourg | D23: =[1]Scoreboards!D47 -> 9.6068265 | E23: =[1]Scoreboards!E47 -> 1.1658026 | F23: =[1]Scoreboards!F47 -> 42.899535 | G23: =[1]Scoreboards!G47 -> -7 | H23: =[1]Scoreboards!H47 -> 4.7502819 | I23: =[1]Scoreboards!I47 -> 0.99971512 | J23: =[1]Scoreboards!J47 -> 1.859 | ... R23: =[1]Scoreboards!R47
C24: =[1]Scoreboards!C48 -> Latvia | D24: =[1]Scoreboards!D48 -> 5.999592 | E24: =[1]Scoreboards!E48 -> 1.2330433 | F24: =[1]Scoreboards!F48 -> 16 | G24: =[1]Scoreboards!G48 -> -14 | H24: =[1]Scoreboards!H48 -> -1.4653542 | I24: =[1]Scoreboards!I48 -> 1.0972955 | J24: =[1]Scoreboards!J48 -> 2.2343 | ... R24: =[1]Scoreboards!R48 -> -0.70583309
C25: =[1]Scoreboards!C49 -> Malta | D25: =[1]Scoreboards!D49 -> 3.7933787 | E25: =[1]Scoreboards!E49 -> 1.0643535 | F25: =[1]Scoreboards!F49 -> 9 | G25: =[1]Scoreboards!G49 -> -33 | H25: =[1]Scoreboards!H49 -> 7.1044426 | I25: =[1]Scoreboards!I49 -> 1.0467049 | J25: =[1]Scoreboards!J49 -> 1.567 | ... R25: =[1]Scoreboards!R49
C26: =[1]Scoreboards!C50 -> Netherlands | D26: =[1]Scoreboards!D50 -> 6.5089294 | E26: =[1]Scoreboards!E50 -> 1.1047078 | F26: =[1]Scoreboards!F50 -> 11.784602 | G26: =[1]Scoreboards!G50 -> 16 | H26: =[1]Scoreboards!H50 -> -1.1256941 | I26: =[1]Scoreboards!I50 -> 0.98462128 | J26: =[1]Scoreboards!J50 -> 1.8192 | ... R26: =[1]Scoreboards!R50 -> 0.9345603
C27: =[1]Scoreboards!C51 -> Portugal | D27: =[1]Scoreboards!D51 -> 8.8910462 | E27: =[1]Scoreboards!E51 -> 1.1934015 | F27: =[1]Scoreboards!F51 -> 23 | G27: =[1]Scoreboards!G51 -> -3 | H27: =[1]Scoreboards!H51 -> -0.26827256 | I27: =[1]Scoreboards!I51 -> 0.93682392 | J27: =[1]Scoreboards!J51 -> 1.2179 | ... R27: =[1]Scoreboards!R51 -> 0.16760519
C28: =[1]Scoreboards!C52 -> Slovenia | D28: =[1]Scoreboards!D52 -> 7.4272261 | E28: =[1]Scoreboards!E52 -> 1.2589321 | F28: =[1]Scoreboards!F52 -> 5 | G28: =[1]Scoreboards!G52 -> -27 | H28: =[1]Scoreboards!H52 -> 4.3490509 | I28: =[1]Scoreboards!I52 -> 0.94143717 | J28: =[1]Scoreboards!J52 -> 1.8096 | ... R28: =[1]Scoreboards!R52 -> -0.55213996
C29: =[1]Scoreboards!C53 -> Slovakia | D29: =[1]Scoreboards!D53 -> 14.850478 | E29: =[1]Scoreboards!E53 -> 1.3035416 | F29: =[1]Scoreboards!F53 -> 9.5503483 | G29: =[1]Scoreboards!G53 -> 9 | H29: =[1]Scoreboards!H53 -> 5.2861324 | I29: =[1]Scoreboards!I53 -> 0.98934568 | J29: =[1]Scoreboards!J53 -> 1.5384 | ... R29: =[1]Scoreboards!R53 -> 0.1050823
C30: =[1]Scoreboards!C54 -> T1 | D30: =[1]Scoreboards!D54 -> 2.5 | E30: =[1]Scoreboards!E54 -> 1 | F30: =[1]Scoreboards!F54 -> 4 | G30: =[1]Scoreboards!G54 -> 0 | H30: =[1]Scoreboards!H54 -> 3 | I30: =[1]Scoreboards!I54 -> 1.05 | J30: =[1]Scoreboards!J54 -> 2 | ... R30: =[1]Scoreboards!R54 -> 0
C31: =[1]Scoreboards!C55 -> T2 | D31: =[1]Scoreboards!D55 -> 5 | E31: =[1]Scoreboards!E55 -> 1.04 | F31: =[1]Scoreboards!F55 -> 10 | G31: =[1]Scoreboards!G55 -> 6 | H31: =[1]Scoreboards!H55 -> 6 | I31: =[1]Scoreboards!I55 -> 1.1 | J31: =[1]Scoreboards!J55 -> 1.5 | ... R31: =[1]Scoreboards!R55 -> 0.36097566
C32: =[1]Scoreboards!C56 -> T3 | D32: =[1]Scoreboards!D56 -> 7.5 | E32: =[1]Scoreboards!E56 -> 1.08 | F32: =[1]Scoreboards!F56 -> 16 | G32: =[1]Scoreboards!G56 -> 12 | H32: =[1]Scoreboards!H56 -> 9 | I32: =[1]Scoreboards!I56 -> 1.15 | J32: =[1]Scoreboards!J56 -> 1 | ... R32: =[1]Scoreboards!R56 -> 0.51167416
C33: Sources: BdP calculations based on SDW and Eurostat data.
C34: Notes:
C35: 1. | D35: =+"The values of the indicators presented in the table above take into account the most recent data available from the different sources for each of the countries at the date of the last update made by DES ("&T4&")."&" Therefore, the reference date of each indicator for each country may differ." -> The values of the indicators presented in the table above take into account the most recent data available from the different sources for each of the countries at the date of the last update made by DES (August 2022). Therefore, the reference date of each indicator for each country may differ.
D37: (see appendix to check the reference date by country and indicator)
C38: 2. | D38: For the indicator HH debt, % of income, it was not possible to obtain data for Luxembourg and Malta. | S38: =ToC!AA23+1 -> 2

Sheet 2.Charts PT SB PI
B2: =ToC!B7 -> 2 | C2: =+ToC!D7 -> Charts for Portuguese indicators (RRE scoreboard)
T3: =+ToC!AB3 -> Scoreboard for residential real estate risks
T4: =+ToC!AB4 -> August 2022
C5: Price indicators
S34: ='1.RRE SB'!S38+1 -> 3

Sheet 2.Charts PT SB LI & HHBS
B2: =ToC!B7 -> 2 | C2: =+ToC!D7 -> Charts for Portuguese indicators (RRE scoreboard)
T3: =+ToC!AB3 -> Scoreboard for residential real estate risks
T4: =+ToC!AB4 -> August 2022
C5: Lending indicators
C18: Household balance sheet indicators
S34: ='2.Charts PT SB PI'!S34+1 -> 4

Sheet 3.PfS
B2: =ToC!B9 -> 3 | C2: =+ToC!D9 -> Scoreboard for potential for spillovers (exposure to RRE)
O3: =+ToC!AB3 -> Scoreboard for residential real estate risks
O4: =+ToC!AB4 -> August 2022
C5: 3.1. Indicators calculated with the reference data of the latest published data for Portugal (indicated in the table)
D7: =[1]Scoreboards!D32 -> Indicators
D8: =[1]PotentialForSpillovers!C2 -> 2022,Q1 | E8: =[1]PotentialForSpillovers!D2 -> 2022,Q1 | F8: =[1]PotentialForSpillovers!E2 -> 2022,Q1 | G8: =[1]PotentialForSpillovers!F2 -> 2022,Q1 | H8: =[1]PotentialForSpillovers!G2 -> 2021,Q4 | I8: =[1]PotentialForSpillovers!H2 -> 2022,Q1
C9: =[1]PotentialForSpillovers!B3 -> Country | D9: =[1]PotentialForSpillovers!C3 -> GFCF dwellings (% of GDP) (11) | E9: =[1]PotentialForSpillovers!D3 -> Bank exposures to RRE (% of GDP) (12) | F9: =[1]PotentialForSpillovers!E3 -> Non-Bank intermediary exposures to RE markets (% of GDP) (13) | G9: =[1]PotentialForSpillovers!F3 -> Bank exposures to RRE (% of capital) (14) | H9: =[1]PotentialForSpillovers!G3 -> Bank exposures to construction and real estate activities (% of capital) (15) | I9: =[1]PotentialForSpillovers!H3 -> Housing wealth (% of GDP) (16)
C10: =[1]PotentialForSpillovers!B4 -> Austria | D10: =[1]PotentialForSpillovers!C4 -> 5.1114306 | E10: =[1]PotentialForSpillovers!D4 -> 31.622862 | F10: =[1]PotentialForSpillovers!E4 -> 2.9878142 | G10: =[1]PotentialForSpillovers!F4 -> 203.47102 | H10: =[1]PotentialForSpillovers!G4 -> 140.52243 | I10: =[1]PotentialForSpillovers!H4 -> 265.32739
C11: =[1]PotentialForSpillovers!B5 -> Belgium | D11: =[1]PotentialForSpillovers!C5 -> 0 | E11: =[1]PotentialForSpillovers!D5 -> 40.353172 | F11: =[1]PotentialForSpillovers!E5 | G11: =[1]PotentialForSpillovers!F5 -> 459.60754 | H11: =[1]PotentialForSpillovers!G5 -> 95.421448 | I11: =[1]PotentialForSpillovers!H5 -> 293.692
C12: =[1]PotentialForSpillovers!B6 -> Cyprus | D12: =[1]PotentialForSpillovers!C6 -> 6.7077273 | E12: =[1]PotentialForSpillovers!D6 -> 34.895306 | F12: =[1]PotentialForSpillovers!E6 | G12: =[1]PotentialForSpillovers!F6 -> 210.01117 | H12: =[1]PotentialForSpillovers!G6 -> 81.448433 | I12: =[1]PotentialForSpillovers!H6 -> 295.00081
C13: =[1]PotentialForSpillovers!B7 -> Germany | D13: =[1]PotentialForSpillovers!C7 -> 7.313808 | E13: =[1]PotentialForSpillovers!D7 -> 40.762668 | F13: =[1]PotentialForSpillovers!E7 -> 13.244911 | G13: =[1]PotentialForSpillovers!F7 -> 228.14104 | H13: =[1]PotentialForSpillovers!G7 -> 113.05528 | I13: =[1]PotentialForSpillovers!H7 -> 257.62322
C14: =[1]PotentialForSpillovers!B8 -> Estonia | D14: =[1]PotentialForSpillovers!C8 -> 4.4143272 | E14: =[1]PotentialForSpillovers!D8 -> 31.176473 | F14: =[1]PotentialForSpillovers!E8 -> 2.7014816 | G14: =[1]PotentialForSpillovers!F8 | H14: =[1]PotentialForSpillovers!G8 | I14: =[1]PotentialForSpillovers!H8 -> 138.29982
C15: =[1]PotentialForSpillovers!B9 -> Spain | D15: =[1]PotentialForSpillovers!C9 -> 5.3466932 | E15: =[1]PotentialForSpillovers!D9 -> 41.408823 | F15: =[1]PotentialForSpillovers!E9 -> 0.14991788 | G15: =[1]PotentialForSpillovers!F9 -> 463.78185 | H15: =[1]PotentialForSpillovers!G9 -> 71.923523 | I15: =[1]PotentialForSpillovers!H9 -> 490.14249
C16: =[1]PotentialForSpillovers!B10 -> Finland | D16: =[1]PotentialForSpillovers!C10 -> 7.3624961 | E16: =[1]PotentialForSpillovers!D10 -> 42.021268 | F16: =[1]PotentialForSpillovers!E10 -> 6.594344 | G16: =[1]PotentialForSpillovers!F10 | H16: =[1]PotentialForSpillovers!G10 -> 224.34447 | I16: =[1]PotentialForSpillovers!H10 -> 158.39254
C17: =[1]PotentialForSpillovers!B11 -> France | D17: =[1]PotentialForSpillovers!C11 -> 6.7668298 | E17: =[1]PotentialForSpillovers!D11 -> 49.882673 | F17: =[1]PotentialForSpillovers!E11 -> 6.8816105 | G17: =[1]PotentialForSpillovers!F11 -> 154.41773 | H17: =[1]PotentialForSpillovers!G11 -> 110.24926 | I17: =[1]PotentialForSpillovers!H11 -> 333.82877
C18: =[1]PotentialForSpillovers!B12 -> Greece | D18: =[1]PotentialForSpillovers!C12 -> 1.3014316 | E18: =[1]PotentialForSpillovers!D12 -> 15.953924 | F18: =[1]PotentialForSpillovers!E12 -> 2.1254575 | G18: =[1]PotentialForSpillovers!F12 -> 190.17502 | H18: =[1]PotentialForSpillovers!G12 -> 60.821244 | I18: =[1]PotentialForSpillovers!H12 -> 278.29699
C19: =[1]PotentialForSpillovers!B13 -> Ireland | D19: =[1]PotentialForSpillovers!C13 -> 2.2452482 | E19: =[1]PotentialForSpillovers!D13 -> 19.114001 | F19: =[1]PotentialForSpillovers!E13 -> 8.1655712 | G19: =[1]PotentialForSpillovers!F13 -> 159.42974 | H19: =[1]PotentialForSpillovers!G13 -> 31.387663 | I19: =[1]PotentialForSpillovers!H13 -> 127.51639
C20: =[1]PotentialForSpillovers!B14 -> Italy | D20: =[1]PotentialForSpillovers!C14 -> 5.0540022 | E20: =[1]PotentialForSpillovers!D14 -> 22.960097 | F20: =[1]PotentialForSpillovers!E14 -> 5.8877298 | G20: =[1]PotentialForSpillovers!F14 -> 280.25725 | H20: =[1]PotentialForSpillovers!G14 -> 92.752754 | I20: =[1]PotentialForSpillovers!H14 -> 296.5097
... C28: =[1]PotentialForSpillovers!B22 -> Slovakia | D28: =[1]PotentialForSpillovers!C22 -> 4.0209055 | E28: =[1]PotentialForSpillovers!D22 -> 39.021829 | F28: =[1]PotentialForSpillovers!E22 -> 2.2214575 | G28: =[1]PotentialForSpillovers!F22 -> 503.02492 | H28: =[1]PotentialForSpillovers!G22 -> 74.21223 | I28: =[1]PotentialForSpillovers!H22 -> 200.19033
C29: Sources: BdP calculations based on SDW data.
N33: ='2.Charts PT SB LI & HHBS'!S34+1 -> 5

Sheet 4.Charts PT PfS
B2: =ToC!B11 -> 4 | C2: =+ToC!D11 -> Charts for Portuguese indicators (potential for spillovers scoreboard)
T3: =+ToC!AB3 -> Scoreboard for residential real estate risks
T4: =+ToC!AB4 -> August 2022
S34: ='3.PfS'!N33+1 -> 6

Sheet 5.Appendix 1 > RRE
B2: =ToC!B13 -> 5 | C2: =+ToC!D13 -> Appendix
T3: =+ToC!AB3 -> Scoreboard for residential real estate risks
T4: =+ToC!AB4 -> August 2022
C5: 5.1. Scoreboard for residential real estate risks - 2021 Q4
D7: =[1]Scoreboards!D32 -> Indicators | N7: =[1]Scoreboards!N31 -> SUMMARY MEASURES | O7: =[2]Scoreboards!O31 -> 0 | P7: =[1]Scoreboards!P31 -> ALTERNATIVE SUMMARY MEASURES | Q7: =[2]Scoreboards!Q31 -> 0 | R7: =[2]Scoreboards!R31 -> 0
N8: =[2]Scoreboards!N32 -> 0 | O8: =[2]Scoreboards!O32 -> 0 | P8: =[2]Scoreboards!P32 -> 0 | Q8: =[2]Scoreboards!Q32 -> 0 | R8: =[2]Scoreboards!R32 -> 0
D9: =[1]Scoreboards!D33 -> Price indicators | E9: =[2]Scoreboards!E33 -> 0 | F9: =[2]Scoreboards!F33 -> 0 | G9: =[2]Scoreboards!G33 -> 0 | H9: =[1]Scoreboards!H33 -> Lending indicators | I9: =[2]Scoreboards!I33 -> 0 | J9: =[2]Scoreboards!J33 -> 0 | K9: =[1]Scoreboards!K33 -> Household balance sheet | L9: =[2]Scoreboards!L33 -> 0 | M9: =[2]Scoreboards!M33 -> 0
C10: =[1]Scoreboards!C34 -> Country | D10: =[1]Scoreboards!D34 -> Residential real estate price index, 36m real growth, % | E10: =[1]Scoreboards!E34 -> Residential price index relative to trend | F10: =[1]Scoreboards!F34 -> House price to income ratio (deviation from historical average in %) | G10: =[1]Scoreboards!G34 -> Econometric Model | H10: =[1]Scoreboards!H34 -> Loans to HH for house purchase, 36m real growth, % | I10: =[1]Scoreboards!I34 -> Loans to HH for HP relative to trend | J10: =[1]Scoreboards!J34 -> HH Loan Spread | ... R10: =[1]Scoreboards!R34 -> Household Balance Sheet Composite Indicator
C11: =[1]Scoreboards!C76 -> Austria | D11: =[1]Scoreboards!D76 -> 6.6131226 | E11: =[1]Scoreboards!E76 -> 1.1283125 | F11: =[1]Scoreboards!F76 -> 47 | G11: =[1]Scoreboards!G76 -> 21 | H11: =[1]Scoreboards!H76 -> 4.9262396 | I11: =[1]Scoreboards!I76 -> 0.98632332 | J11: =[1]Scoreboards!J76 -> 1.5465 | ... R11: =[1]Scoreboards!R76 -> -0.029115749
C12: =[1]Scoreboards!C77 -> Belgium | D12: =[1]Scoreboards!D77 -> 4.3114252 | E12: =[1]Scoreboards!E77 -> 1.0130572 | F12: =[1]Scoreboards!F77 | G12: =[1]Scoreboards!G77 -> 3 | H12: =[1]Scoreboards!H77 -> 6.305044 | I12: =[1]Scoreboards!I77 -> 1.1312958 | J12: =[1]Scoreboards!J77 -> 1.6933 | ... R12: =[1]Scoreboards!R77 -> -0.028613325
C13: =[1]Scoreboards!C78 -> Cyprus | D13: =[1]Scoreboards!D78 -> 0.60593307 | E13: =[1]Scoreboards!E78 -> 1.1625732 | F13: =[1]Scoreboards!F78 -> -7 | G13: =[1]Scoreboards!G78 -> -15 | H13: =[1]Scoreboards!H78 -> 1.1015358 | I13: =[1]Scoreboards!I78 -> 0.77185543 | J13: =[1]Scoreboards!J78 -> 2.1131 | ... R13: =[1]Scoreboards!R78
C14: =[1]Scoreboards!C79 -> Germany | D14: =[1]Scoreboards!D79 -> 7.5420621 | E14: =[1]Scoreboards!E79 -> 1.1674817 | F14: =[1]Scoreboards!F79 -> 29 | G14: =[1]Scoreboards!G79 -> 20 | H14: =[1]Scoreboards!H79 -> 4.3357783 | I14: =[1]Scoreboards!I79 -> 1.1148892 | J14: =[1]Scoreboards!J79 -> 1.7895 | ... R14: =[1]Scoreboards!R79 -> 0.00888118
C15: =[1]Scoreboards!C80 -> Estonia | D15: =[1]Scoreboards!D80 -> 6.6192036 | E15: =[1]Scoreboards!E80 -> 1.1715435 | F15: =[1]Scoreboards!F80 -> 26 | G15: =[1]Scoreboards!G80 -> 12 | H15: =[1]Scoreboards!H80 -> 4.4502087 | I15: =[1]Scoreboards!I80 -> 1.0999302 | J15: =[1]Scoreboards!J80 -> 1.6025 | ... R15: =[1]Scoreboards!R80
C16: =[1]Scoreboards!C81 -> Spain | D16: =[1]Scoreboards!D81 | E16: =[1]Scoreboards!E81 | F16: =[1]Scoreboards!F81 -> 11 | G16: =[1]Scoreboards!G81 -> 4 | H16: =[1]Scoreboards!H81 -> -2.3150783 | I16: =[1]Scoreboards!I81 -> 0.87931619 | J16: =[1]Scoreboards!J81 -> 1.3123 | ... R16: =[1]Scoreboards!R81 -> -0.082857891
C17: =[1]Scoreboards!C82 -> Finland | D17: =[1]Scoreboards!D82 -> 1.2623237 | E17: =[1]Scoreboards!E82 -> 1.0120206 | F17: =[1]Scoreboards!F82 | G17: =[1]Scoreboards!G82 -> 9 | H17: =[1]Scoreboards!H82 -> 1.9396364 | I17: =[1]Scoreboards!I82 -> 0.94881493 | J17: =[1]Scoreboards!J82 -> 0.852 | ... R17: =[1]Scoreboards!R82 -> 0.66412425
C18: =[1]Scoreboards!C83 -> France | D18: =[1]Scoreboards!D83 -> 4.3478543 | E18: =[1]Scoreboards!E83 -> 1.0208601 | F18: =[1]Scoreboards!F83 | G18: =[1]Scoreboards!G83 -> -3 | H18: =[1]Scoreboards!H83 -> 5.1432146 | I18: =[1]Scoreboards!I83 -> 1.0349418 | J18: =[1]Scoreboards!J83 -> 1.1269 | ... R18: =[1]Scoreboards!R83 -> 0.14820434
C19: =[1]Scoreboards!C84 -> Greece | D19: =[1]Scoreboards!D84 -> 6.3918538 | E19: =[1]Scoreboards!E84 -> 1.1560282 | F19: =[1]Scoreboards!F84 | G19: =[1]Scoreboards!G84 | H19: =[1]Scoreboards!H84 -> -8.8198515 | I19: =[1]Scoreboards!I84 -> 0.5113334 | J19: =[1]Scoreboards!J84 -> 2.6377 | ... R19: =[1]Scoreboards!R84
C20: =[1]Scoreboards!C85 -> Ireland | D20: =[1]Scoreboards!D85 | E20: =[1]Scoreboards!E85 | F20: =[1]Scoreboards!F85 -> 5 | G20: =[1]Scoreboards!G85 -> -13 | H20: =[1]Scoreboards!H85 -> -3.2596816 | I20: =[1]Scoreboards!I85 -> 0.9424018 | J20: =[1]Scoreboards!J85 -> 3.0769 | ... R20: =[1]Scoreboards!R85 -> -0.011598563
C21: =[1]Scoreboards!C86 -> Italy | D21: =[1]Scoreboards!D86 | E21: =[1]Scoreboards!E86 | F21: =[1]Scoreboards!F86 -> -6 | G21: =[1]Scoreboards!G86 -> -13 | H21: =[1]Scoreboards!H86 -> 1.5068177 | I21: =[1]Scoreboards!I86 -> 0.93832823 | J21: =[1]Scoreboards!J86 -> 0.8305 | ... R21: =[1]Scoreboards!R86 -> -0.47936834
C22: =[1]Scoreboards!C87 -> Lithuania | D22: =[1]Scoreboards!D87 -> 5.7431488 | E22: =[1]Scoreboards!E87 -> 1.0414995 | F22: =[1]Scoreboards!F87 -> 4 | G22: =[1]Scoreboards!G87 -> 0 | H22: =[1]Scoreboards!H87 -> 6.0168256 | I22: =[1]Scoreboards!I87 -> 1.0167862 | J22: =[1]Scoreboards!J87 -> 1.9933 | ... R22: =[1]Scoreboards!R87
... C32: =[1]Scoreboards!C97 -> T3 | D32: =[1]Scoreboards!D97 -> 7.5 | E32: =[1]Scoreboards!E97 -> 1.08 | F32: =[1]Scoreboards!F97 -> 16 | G32: =[1]Scoreboards!G97 -> 12 | H32: =[1]Scoreboards!H97 -> 9 | I32: =[1]Scoreboards!I97 -> 1.15 | J32: =[1]Scoreboards!J97 -> 1 | ... R32: =[1]Scoreboards!R97 -> 0.51167416
C33: Sources: BdP calculations based on SDW and Eurostat data.
S34: ='4.Charts PT PfS'!S34+1 -> 7

Sheet 5.Appendix 2 > PfS
B2: =ToC!B13 -> 5 | C2: =+ToC!D13 -> Appendix
O3: =+ToC!AB3 -> Scoreboard for residential real estate risks
O4: =+ToC!AB4 -> August 2022
C5: 5.2. Scoreboard for potential for spillovers (exposure to residential real state) - 2021 Q4
D7: =[1]Scoreboards!D32 -> Indicators
D8: =[1]PotentialForSpillovers!$C$25 -> 2021,Q4 | E8: =[1]PotentialForSpillovers!$C$25 -> 2021,Q4 | F8: =[1]PotentialForSpillovers!$C$25 -> 2021,Q4 | G8: =[1]PotentialForSpillovers!$C$25 -> 2021,Q4 | H8: =[1]PotentialForSpillovers!$C$25 -> 2021,Q4 | I8: =[1]PotentialForSpillovers!$C$25 -> 2021,Q4
C9: =[1]PotentialForSpillovers!B26 -> Country | D9: =[1]PotentialForSpillovers!C26 -> GFCF dwellings (% of GDP) (11) | E9: =[1]PotentialForSpillovers!D26 -> Bank exposures to RRE (% of GDP) (12) | F9: =[1]PotentialForSpillovers!E26 -> Non-Bank intermediary exposures to RE markets (% of GDP) (13) | G9: =[1]PotentialForSpillovers!F26 -> Bank exposures to RRE (% of capital) (14) | H9: =[1]PotentialForSpillovers!G26 -> Bank exposures to construction and real estate activities (% of capital) (15) | I9: =[1]PotentialForSpillovers!H26 -> Housing wealth (% of GDP) (16)
C10: =[1]PotentialForSpillovers!B27 -> Austria | D10: =[1]PotentialForSpillovers!C27 -> 5.1823633 | E10: =[1]PotentialForSpillovers!D27 -> 32.295628 | F10: =[1]PotentialForSpillovers!E27 -> 3.0513207 | G10: =[1]PotentialForSpillovers!F27 -> 201.15255 | H10: =[1]PotentialForSpillovers!G27 -> 140.52243 | I10: =[1]PotentialForSpillovers!H27 -> 263.92381
C11: =[1]PotentialForSpillovers!B28 -> Belgium | D11: =[1]PotentialForSpillovers!C28 -> 0 | E11: =[1]PotentialForSpillovers!D28 -> 40.795528 | F11: =[1]PotentialForSpillovers!E28 | G11: =[1]PotentialForSpillovers!F28 -> 440.37427 | H11: =[1]PotentialForSpillovers!G28 -> 95.421448 | I11: =[1]PotentialForSpillovers!H28 -> 298.53326
C12: =[1]PotentialForSpillovers!B29 -> Cyprus | D12: =[1]PotentialForSpillovers!C29 -> 6.9119373 | E12: =[1]PotentialForSpillovers!D29 -> 35.777221 | F12: =[1]PotentialForSpillovers!E29 | G12: =[1]PotentialForSpillovers!F29 -> 197.78432 | H12: =[1]PotentialForSpillovers!G29 -> 81.448433 | I12: =[1]PotentialForSpillovers!H29 -> 301.08194
C13: =[1]PotentialForSpillovers!B30 -> Germany | D13: =[1]PotentialForSpillovers!C30 -> 7.177622 | E13: =[1]PotentialForSpillovers!D30 -> 41.063733 | F13: =[1]PotentialForSpillovers!E30 -> 13.237982 | G13: =[1]PotentialForSpillovers!F30 -> 217.77374 | H13: =[1]PotentialForSpillovers!G30 -> 113.05528 | I13: =[1]PotentialForSpillovers!H30 -> 260.23985
C14: =[1]PotentialForSpillovers!B31 -> Estonia | D14: =[1]PotentialForSpillovers!C31 -> 4.7384235 | E14: =[1]PotentialForSpillovers!D31 -> 31.497522 | F14: =[1]PotentialForSpillovers!E31 -> 2.7296982 | G14: =[1]PotentialForSpillovers!F31 | H14: =[1]PotentialForSpillovers!G31 | I14: =[1]PotentialForSpillovers!H31 -> 140.71679
C15: =[1]PotentialForSpillovers!B32 -> Spain | D15: =[1]PotentialForSpillovers!C32 -> 5.3847807 | E15: =[1]PotentialForSpillovers!D32 -> 42.335961 | F15: =[1]PotentialForSpillovers!E32 -> 0.15202525 | G15: =[1]PotentialForSpillovers!F32 -> 462.06683 | H15: =[1]PotentialForSpillovers!G32 -> 71.923523 | I15: =[1]PotentialForSpillovers!H32 -> 490.45331
C16: =[1]PotentialForSpillovers!B33 -> Finland | D16: =[1]PotentialForSpillovers!C33 -> 7.1546468 | E16: =[1]PotentialForSpillovers!D33 -> 42.789075 | F16: =[1]PotentialForSpillovers!E33 -> 6.3472682 | G16: =[1]PotentialForSpillovers!F33 -> 607.82888 | H16: =[1]PotentialForSpillovers!G33 -> 224.34447 | I16: =[1]PotentialForSpillovers!H33 -> 159.51135
C17: =[1]PotentialForSpillovers!B34 -> France | D17: =[1]PotentialForSpillovers!C34 -> 6.7137985 | E17: =[1]PotentialForSpillovers!D34 -> 50.242628 | F17: =[1]PotentialForSpillovers!E34 -> 6.5048953 | G17: =[1]PotentialForSpillovers!F34 -> 151.98885 | H17: =[1]PotentialForSpillovers!G34 -> 110.24926 | I17: =[1]PotentialForSpillovers!H34 -> 336.70789
C18: =[1]PotentialForSpillovers!B35 -> Greece | D18: =[1]PotentialForSpillovers!C35 -> 1.2639819 | E18: =[1]PotentialForSpillovers!D35 -> 16.692542 | F18: =[1]PotentialForSpillovers!E35 -> 2.1705392 | G18: =[1]PotentialForSpillovers!F35 -> 185.29343 | H18: =[1]PotentialForSpillovers!G35 -> 60.821244 | I18: =[1]PotentialForSpillovers!H35 -> 284.47888
C19: =[1]PotentialForSpillovers!B36 -> Ireland | D19: =[1]PotentialForSpillovers!C36 -> 2.0991527 | E19: =[1]PotentialForSpillovers!D36 -> 16.470263 | F19: =[1]PotentialForSpillovers!E36 -> 8.3784633 | G19: =[1]PotentialForSpillovers!F36 -> 158.73317 | H19: =[1]PotentialForSpillovers!G36 -> 31.387663 | I19: =[1]PotentialForSpillovers!H36 -> 131.43055
C20: =[1]PotentialForSpillovers!B37 -> Italy | D20: =[1]PotentialForSpillovers!C37 -> 4.8532385 | E20: =[1]PotentialForSpillovers!D37 -> 23.085496 | F20: =[1]PotentialForSpillovers!E37 -> 5.9861383 | G20: =[1]PotentialForSpillovers!F37 -> 267.16304 | H20: =[1]PotentialForSpillovers!G37 -> 92.752754 | I20: =[1]PotentialForSpillovers!H37 -> 298.19949
... C28: =[1]PotentialForSpillovers!B45 -> Slovakia | D28: =[1]PotentialForSpillovers!C45 -> 3.9620578 | E28: =[1]PotentialForSpillovers!D45 -> 38.77165 | F28: =[1]PotentialForSpillovers!E45 -> 2.1381037 | G28: =[1]PotentialForSpillovers!F45 -> 504.75138 | H28: =[1]PotentialForSpillovers!G45 -> 74.21223 | I28: =[1]PotentialForSpillovers!H45 -> 188.8588
C29: Sources: BdP calculations based on SDW data.
N33: ='5.Appendix 1 > RRE'!S34+1 -> 8

Sheet 5.Appendix 3 > Data
B2: =ToC!$B$13 -> 5 | C2: =+ToC!D13 -> Appendix
R3: =+ToC!AB3 -> Scoreboard for residential real estate risks
R4: =+ToC!AB4 -> August 2022
C5: 5.3. Table with the reference dates of the data available in the table 1.1.
D7: =[1]Scoreboards!D32 -> Indicators
D9: =[1]Scoreboards!D33 -> Price indicators | E9: =[2]Scoreboards!E33 -> 0 | F9: =[2]Scoreboards!F33 -> 0 | G9: =[2]Scoreboards!G33 -> 0 | H9: =[1]Scoreboards!H33 -> Lending indicators | I9: =[2]Scoreboards!I33 -> 0 | J9: =[2]Scoreboards!J33 -> 0 | K9: =[1]Scoreboards!K33 -> Household balance sheet | L9: =[2]Scoreboards!L33 -> 0 | M9: =[2]Scoreboards!M33 -> 0
C10: =[1]Scoreboards!C34 -> Country | D10: =[1]Scoreboards!D34 -> Residential real estate price index, 36m real growth, % | E10: =[1]Scoreboards!E34 -> Residential price index relative to trend | F10: =[1]Scoreboards!F34 -> House price to income ratio (deviation from historical average in %) | G10: =[1]Scoreboards!G34 -> Econometric Model | H10: =[1]Scoreboards!H34 -> Loans to HH for house purchase, 36m real growth, % | I10: =[1]Scoreboards!I34 -> Loans to HH for HP relative to trend | J10: =[1]Scoreboards!J34 -> HH Loan Spread | ... M10: =[1]Scoreboards!M34 -> Debt service to income ratio for HH, %
C11: =[1]Scoreboards!C35 -> Austria | D11: =[1]Scoreboards!D109 -> 2022,Q2 | E11: =[1]Scoreboards!E109 -> 2022,Q2 | F11: =[1]Scoreboards!F109 -> 2022,Q1 | G11: =[1]Scoreboards!G109 -> 2022,Q1 | H11: =[1]Scoreboards!H109 -> 2022,Q2 | I11: =[1]Scoreboards!I109 -> 2022,Q2 | J11: =[1]Scoreboards!J109 -> 2022,Q2 | K11: =[1]Scoreboards!K109 -> 2022,Q1 | ... M11: =[1]Scoreboards!M109 -> 2022,Q1
C12: =[1]Scoreboards!C36 -> Belgium | D12: =[1]Scoreboards!D110 -> 2022,Q1 | E12: =[1]Scoreboards!E110 -> 2022,Q1 | F12: =[1]Scoreboards!F110 -> 2020,Q4 | G12: =[1]Scoreboards!G110 -> 2022,Q1 | H12: =[1]Scoreboards!H110 -> 2022,Q2 | I12: =[1]Scoreboards!I110 -> 2022,Q2 | J12: =[1]Scoreboards!J110 -> 2022,Q2 | K12: =[1]Scoreboards!K110 -> 2022,Q1 | ... M12: =[1]Scoreboards!M110 -> 2022,Q1
C13: =[1]Scoreboards!C37 -> Cyprus | D13: =[1]Scoreboards!D111 -> 2022,Q1 | E13: =[1]Scoreboards!E111 -> 2022,Q1 | F13: =[1]Scoreboards!F111 -> 2022,Q1 | G13: =[1]Scoreboards!G111 -> 2022,Q1 | H13: =[1]Scoreboards!H111 -> 2022,Q2 | I13: =[1]Scoreboards!I111 -> 2022,Q2 | J13: =[1]Scoreboards!J111 -> 2022,Q2 | K13: =[1]Scoreboards!K111 -> 2020,Q4 | ... M13: =[1]Scoreboards!M111 -> 2022,Q1
C14: =[1]Scoreboards!C38 -> Germany | D14: =[1]Scoreboards!D112 -> 2022,Q2 | E14: =[1]Scoreboards!E112 -> 2022,Q2 | F14: =[1]Scoreboards!F112 -> 2022,Q1 | G14: =[1]Scoreboards!G112 -> 2022,Q1 | H14: =[1]Scoreboards!H112 -> 2022,Q2 | I14: =[1]Scoreboards!I112 -> 2022,Q2 | J14: =[1]Scoreboards!J112 -> 2022,Q2 | K14: =[1]Scoreboards!K112 -> 2022,Q1 | ... M14: =[1]Scoreboards!M112 -> 2022,Q1
C15: =[1]Scoreboards!C39 -> Estonia | D15: =[1]Scoreboards!D113 -> 2022,Q2 | E15: =[1]Scoreboards!E113 -> 2022,Q2 | F15: =[1]Scoreboards!F113 -> 2022,Q1 | G15: =[1]Scoreboards!G113 -> 2022,Q1 | H15: =[1]Scoreboards!H113 -> 2022,Q2 | I15: =[1]Scoreboards!I113 -> 2022,Q2 | J15: =[1]Scoreboards!J113 -> 2022,Q2 | K15: =[1]Scoreboards!K113 -> 2020,Q4 | ... M15: =[1]Scoreboards!M113 -> 2022,Q1
C16: =[1]Scoreboards!C40 -> Spain | D16: =[1]Scoreboards!D114 -> 2018,Q4 | E16: =[1]Scoreboards!E114 -> 2018,Q4 | F16: =[1]Scoreboards!F114 -> 2022,Q1 | G16: =[1]Scoreboards!G114 -> 2022,Q1 | H16: =[1]Scoreboards!H114 -> 2022,Q2 | I16: =[1]Scoreboards!I114 -> 2022,Q2 | J16: =[1]Scoreboards!J114 -> 2022,Q2 | K16: =[1]Scoreboards!K114 -> 2022,Q1 | ... M16: =[1]Scoreboards!M114 -> 2022,Q1
C17: =[1]Scoreboards!C41 -> Finland | D17: =[1]Scoreboards!D115 -> 2022,Q1 | E17: =[1]Scoreboards!E115 -> 2022,Q1 | F17: =[1]Scoreboards!F115 -> 2020,Q4 | G17: =[1]Scoreboards!G115 -> 2022,Q1 | H17: =[1]Scoreboards!H115 -> 2022,Q2 | I17: =[1]Scoreboards!I115 -> 2022,Q2 | J17: =[1]Scoreboards!J115 -> 2022,Q2 | K17: =[1]Scoreboards!K115 -> 2022,Q1 | ... M17: =[1]Scoreboards!M115 -> 2022,Q1
C18: =[1]Scoreboards!C42 -> France | D18: =[1]Scoreboards!D116 -> 2022,Q1 | E18: =[1]Scoreboards!E116 -> 2022,Q1 | F18: =[1]Scoreboards!F116 -> 2020,Q4 | G18: =[1]Scoreboards!G116 -> 2022,Q1 | H18: =[1]Scoreboards!H116 -> 2022,Q2 | I18: =[1]Scoreboards!I116 -> 2022,Q2 | J18: =[1]Scoreboards!J116 -> 2022,Q2 | K18: =[1]Scoreboards!K116 -> 2022,Q1 | ... M18: =[1]Scoreboards!M116 -> 2022,Q1
C19: =[1]Scoreboards!C43 -> Greece | D19: =[1]Scoreboards!D117 -> 2022,Q1 | E19: =[1]Scoreboards!E117 -> 2022,Q1 | F19: =[1]Scoreboards!F117 -> 2020,Q4 | G19: =[1]Scoreboards!G117 -> 2018,Q4 | H19: =[1]Scoreboards!H117 -> 2022,Q2 | I19: =[1]Scoreboards!I117 -> 2022,Q2 | J19: =[1]Scoreboards!J117 -> 2022,Q2 | K19: =[1]Scoreboards!K117 -> 2021,Q3 | ... M19: =[1]Scoreboards!M117 -> 2022,Q1
C20: =[1]Scoreboards!C44 -> Ireland | D20: =[1]Scoreboards!D118 -> 2018,Q4 | E20: =[1]Scoreboards!E118 -> 2018,Q4 | F20: =[1]Scoreboards!F118 -> 2022,Q1 | G20: =[1]Scoreboards!G118 -> 2022,Q1 | H20: =[1]Scoreboards!H118 -> 2022,Q2 | I20: =[1]Scoreboards!I118 -> 2022,Q2 | J20: =[1]Scoreboards!J118 -> 2022,Q2 | K20: =[1]Scoreboards!K118 -> 2022,Q1 | ... M20: =[1]Scoreboards!M118 -> 2022,Q1
C21: =[1]Scoreboards!C45 -> Italy | D21: =[1]Scoreboards!D119 -> 2018,Q4 | E21: =[1]Scoreboards!E119 -> 2018,Q4 | F21: =[1]Scoreboards!F119 -> 2022,Q1 | G21: =[1]Scoreboards!G119 -> 2022,Q1 | H21: =[1]Scoreboards!H119 -> 2022,Q2 | I21: =[1]Scoreboards!I119 -> 2022,Q2 | J21: =[1]Scoreboards!J119 -> 2022,Q2 | K21: =[1]Scoreboards!K119 -> 2022,Q1 | ... M21: =[1]Scoreboards!M119 -> 2022,Q1
C22: =[1]Scoreboards!C46 -> Lithuania | D22: =[1]Scoreboards!D120 -> 2022,Q1 | E22: =[1]Scoreboards!E120 -> 2022,Q1 | F22: =[1]Scoreboards!F120 -> 2022,Q1 | G22: =[1]Scoreboards!G120 -> 2022,Q1 | H22: =[1]Scoreboards!H120 -> 2022,Q2 | I22: =[1]Scoreboards!I120 -> 2022,Q2 | J22: =[1]Scoreboards!J120 -> 2022,Q2 | K22: =[1]Scoreboards!K120 -> 2020,Q4 | ... M22: =[1]Scoreboards!M120 -> 2022,Q1
... C29: =[1]Scoreboards!C53 -> Slovakia | D29: =[1]Scoreboards!D127 -> 2022,Q1 | E29: =[1]Scoreboards!E127 -> 2022,Q1 | F29: =[1]Scoreboards!F127 -> 2020,Q4 | G29: =[1]Scoreboards!G127 -> 2022,Q1 | H29: =[1]Scoreboards!H127 -> 2022,Q2 | I29: =[1]Scoreboards!I127 -> 2022,Q2 | J29: =[1]Scoreboards!J127 -> 2022,Q2 | K29: =[1]Scoreboards!K127 -> 2020,Q4 | ... M29: =[1]Scoreboards!M127 -> 2022,Q1
Q34: ='5.Appendix 2 > PfS'!N33+1 -> 9

Sheet 5.Appendix 4 > Formulas & Metad
B2: =ToC!B13 -> 5 | C2: =+ToC!D13 -> Appendix
S3: =+ToC!AB3 -> Scoreboard for residential real estate risks
S4: =+ToC!AB4 -> August 2022
C5: 5.4. Scoreboard for residential real estate risks - Formulas and metadata
C7: =+[1]Formulas!B2 -> Indicator | G7: =+[1]Formulas!C2 -> Description
C8: =+[1]Formulas!B3 -> Residential Real Estate price growth | G8: =+[1]Formulas!C3 -> Residential property prices (Nominal house prices. Index with base year 2015. 36 months growth, in %). New and Existing dwellings/Existing dwellings/New and Existing Flats*; Residential property in good & poor condition; Whole country; Neither seasonally nor working day adjusted.
C10: =+[1]Formulas!B4 -> Residential Price Index relative to trend | G10: =+[1]Formulas!C4 -> Residential property prices (Nominal house prices. Index with base year 2015). New and Existing dwellings/Existing dwellings/New and Existing Flats*; Residential property in good & poor condition; Whole country; Neither seasonally nor working day adjusted.
C12: =+[1]Formulas!B5 -> House price to income ratio | G12: =+[1]Formulas!C5 -> Estimates of the over/undervaluation of residential property prices - House price to income ratio (deviation from its average since January 1996).
C17: =+[1]Formulas!B7 -> Econometric model | G17: =+[1]Formulas!C7 -> Estimates of the over/undervaluation of residential property prices: Model-based valuation measures (residual - Bayesian static equation).
C19: =+[1]Formulas!B8 -> Loans to households for house purchases growth | G19: =+[1]Formulas!C8 -> Index of notional stocks. 36 months growth, in %. Lending for house purchase. Total maturity. Households and non-profit institutions serving households (S.14 and S.15) sector. Neither seasonally nor working day adjusted (Balance Sheet Items).
C21: =+[1]Formulas!B9 -> Loans to households for house purchases relative to trend | G21: =+[1]Formulas!C9 -> Outstanding amounts at the end of period (stocks). Lending for house purchase. Total maturity. Households and non-profit institutions serving households (S.14 and S.15) sector. Neither seasonally nor working day adjusted (Balance Sheet Items).
C23: =+[1]Formulas!B10 -> Spread on household loans | G23: =+[1]Formulas!C10 -> Lending for house purchase excluding revolving loans and overdrafts convenience and extended credit card debt. Up to 1/From 1 to 5/From 5 to 10/Over 10 years initial rate fixation. Households and non-profit institutions serving households (S.14 and S.15) sector.
C25: =+[1]Formulas!B11 -> Household debt to income | G25: =+[1]Formulas!C11 -> Household debt to income ratio, in %. Households and non profit institutions serving households (NPISH). Closing balance sheet/Positions/Stocks. Loans. All original maturities. Counterpart area World (all entities including reference area). Neither seasonally adjusted nor calendar adjusted data.
C27: =+[1]Formulas!B12 -> Household financial assets to debt | G27: =+[1]Formulas!C12 -> Household financial assets to debt ratio, in %. Households and non profit institutions serving households (NPISH). Closing balance sheet/Positions/Stocks. Loans. All original maturities. Counterpart area World (all entities including reference area). Neither seasonally adjusted nor calendar adjusted data.
C29: =+[1]Formulas!B13 -> Debt service to income
R32: ='5.Appendix 3 > Data'!Q34+1 -> 10
